Workbook

Sheet 1. Notice
A1: MODÈLE FINANCIER ETI BTP BÂTIMENTS — NOTICE D'UTILISATION
A3: Périmètre | B3: Entreprise de BTP — Spécialité Bâtiments (publics, logements, tertiaire) — Zone UEMOA/CEMAC
A4: Profil | B4: ETI — 10-20 chantiers actifs, CA 20-80 Md FCFA/an, marchés publics et institutionnels
A5: Horizon | B5: 5 années (Y1 mensuel + Y2 à Y5 annuels) — projets pluriannuels
A6: Devise | B6: FCFA — Reconnaissance CA à l'avancement (POC) selon IFRS 15 / SYSCOHADA
A8: STRUCTURE DU CLASSEUR
A9: Feuille | B9: Contenu
A10: 1. Notice | B10: Mode d'emploi, code couleurs, hypothèses-clés
A11: 2. Hypothèses | B11: Tous les inputs pilotables : macro, commercial, opérations, financement
A12: 3. Pipeline & Backlog | B12: Carnet de commandes, taux de transformation appels d'offres
A13: 4. Portefeuille chantiers | B13: Catalogue détaillé des 12 chantiers types avec planning d'avancement
A14: 5. Décomptes & encaissements | B14: Reconnaissance CA mensuelle + plan d'encaissement (avances, RG, délais Etat)
A15: 6. BFR & cautions | B15: Avance démarrage, retenues garantie, cautions bancaires et leurs coûts
A16: 7. Sous-traitance & cotraitance | B16: Quote-part ST/CT, marge groupement, coûts associés
A17: 8. Parc matériel | B17: Engins, amortissements, location vs propriété, ratios d'utilisation
A18: 9. Charges fixes & RH | B18: Masse salariale par pôle, charges structure
A19: 10. CAPEX & Amortissements | B19: Investissements matériel et structure, plan d'amortissement
A20: 11. P&L | B20: Compte de résultat — CA → Marge brute chantier → EBITDA → EBIT → Net
... A23: 14. Scénarios | B23: Pessimiste / Base / Optimiste — sensibilité sur paramètres clés
A26: CODE COULEURS (conventions financières)
A27: Convention | B27: Signification
A28: Cellule bleue sur fond jaune | B28: Input modifiable — hypothèse à piloter
A29: Texte noir | B29: Formule de calcul interne à la feuille
A30: Texte vert | B30: Lien vers une autre feuille du classeur
A31: Fond marine + texte blanc | B31: Total ou sous-total agrégé
A32: Fond or pâle + texte marine | B32: Sous-total intermédiaire
A35: POINTS DE VIGILANCE BTP
A36: • Reconnaissance CA à l'avancement (POC) : le revenu comptable diffère du flux de trésorerie ; bien distinguer P&L et trésorerie.
A37: • Délais de paiement Etat (DSO) : 90 à 180 jours en moyenne UEMOA/CEMAC, parfois plus selon arriérés budgétaires.
A38: • Retenue de garantie (5 à 10%) : libérée après réception définitive (DGD), généralement 12 mois après réception provisoire.
A39: • Cautions bancaires : commissions 1-3% l'an + dépôt de contre-garantie 10-25% → coût financier significatif à intégrer.
A40: • BFR négatif possible en phase d'avance de démarrage, fortement positif en pleine exécution → tension de trésorerie.
A41: • Avenants & révision de prix : prévoir 5 à 15% du marché initial, formule de révision indexée (généralement P0+P1·M/M0+P2·S/S0).
A42: • Marge brute chantier visée 12-18% ; après FG et frais financiers, marge nette cible 4-8%.

Sheet 2. Hypothèses
A1: HYPOTHÈSES — PARAMÈTRES PILOTABLES (5 ans)
A3: Paramètre | B3: Unité | C3: Année 1 | D3: Année 2 | E3: Année 3 | F3: Année 4 | G3: Année 5 | H3: Commentaire
A4: MACRO-ÉCONOMIE & FISCAL
A5: Taux d'inflation (BTP) | B5: % | C5: 0.045 | D5: 0.04 | E5: 0.035 | F5: 0.035 | G5: 0.03 | H5: Indice BT général UEMOA
A6: Taux d'IS | B6: % | C6: 0.3 | D6: 0.3 | E6: 0.3 | F6: 0.3 | G6: 0.3 | H6: Impôt sur les sociétés zone UEMOA/CEMAC
A7: Taux TVA | B7: % | C7: 0.18 | D7: 0.18 | E7: 0.18 | F7: 0.18 | G7: 0.18 | H7: TVA standard
A8: Taux Euribor / référence | B8: % | C8: 0.04 | D8: 0.04 | E8: 0.035 | F8: 0.035 | G8: 0.03 | H8: Référence financière
A9: COMMERCIAL & PIPELINE
A10: Appels d'offres soumis | B10: nb/an | C10: 28 | D10: 35 | E10: 42 | F10: 48 | G10: 55 | H10: Volume d'AO étudiés et chiffrés
A11: Taux de transformation AO | B11: % | C11: 0.32 | D11: 0.35 | E11: 0.38 | F11: 0.4 | G11: 0.42 | H11: Hit-rate moyen
A12: Valeur moyenne chantier signé | B12: FCFA | C12: 3500000000 | D12: 4200000000 | E12: 5000000000 | F12: 5800000000 | G12: 6500000000 | H12: Ticket moyen marché
A13: Durée moyenne chantier | B13: mois | C13: 18 | D13: 20 | E13: 22 | F13: 24 | G13: 24 | H13: Exécution physique
A14: Backlog initial (carnet entrée Y1) | B14: FCFA | C14: 35000000000 | D14: 0 | E14: 0 | F14: 0 | G14: 0 | H14: Carnet de commandes au 01/01
A15: Coût commercial / AO étudié | B15: FCFA | C15: 4500000 | D15: 4800000 | E15: 5200000 | F15: 5500000 | G15: 5800000 | H15: Coût bureau d'études + ingénierie d'offres
A16: STRUCTURE PRIX & MARGES CHANTIER
A17: Marge brute chantier visée | B17: % | C17: 0.14 | D17: 0.15 | E17: 0.16 | F17: 0.16 | G17: 0.17 | H17: Cible avant FG et frais financiers
A18: Avenants & révision prix | B18: % du marché | C18: 0.08 | D18: 0.09 | E18: 0.1 | F18: 0.1 | G18: 0.1 | H18: Avenants techniques + révision prix formule P0/P1/P2/S
A19: Marge sur avenants | B19: % | C19: 0.18 | D19: 0.19 | E19: 0.2 | F19: 0.2 | G19: 0.2 | H19: Meilleure marge sur avenants (moins compétitif)
A20: Réclamations recouvrées | B20: % du marché | C20: 0.015 | D20: 0.02 | E20: 0.02 | F20: 0.02 | G20: 0.02 | H20: Claims aboutis / marché initial
A21: DÉCOMPOSITION COÛTS DIRECTS CHANTIER
A22: Part matériaux | B22: % des coûts directs | C22: 0.36 | D22: 0.36 | E22: 0.35 | F22: 0.35 | G22: 0.35 | H22: Ciment, acier, agrégats, second œuvre
A23: Part main d'œuvre directe | B23: % des coûts directs | C23: 0.22 | D23: 0.22 | E23: 0.21 | F23: 0.21 | G23: 0.2 | H23: Ouvriers, chefs d'équipe
A24: Part sous-traitance | B24: % des coûts directs | C24: 0.22 | D24: 0.23 | E24: 0.24 | F24: 0.25 | G24: 0.26 | H24: ST lots techniques
A25: Part matériel & engins | B25: % des coûts directs | C25: 0.1 | D25: 0.1 | E25: 0.11 | F25: 0.11 | G25: 0.12 | H25: Location + amort + carburant
A26: Part frais de chantier | B26: % des coûts directs | C26: 0.1 | D26: 0.09 | E26: 0.09 | F26: 0.08 | G26: 0.07 | H26: Installation, encadrement, sécurité, divers
A27: SOUS-TRAITANCE & COTRAITANCE
A28: Marge ST récupérée (mark-up) | B28: % | C28: 0.08 | D28: 0.09 | E28: 0.1 | F28: 0.1 | G28: 0.1 | H28: Marge dégagée sur la ST par rapport au coût
A29: Part chantiers en cotraitance | B29: % | C29: 0.25 | D29: 0.3 | E29: 0.32 | F29: 0.35 | G29: 0.35 | H29: Chantiers exécutés en groupement
A30: Quote-part moyenne en cotraitance | B30: % | C30: 0.55 | D30: 0.55 | E30: 0.55 | F30: 0.55 | G30: 0.55 | H30: Quote-part de l'entreprise dans groupement
A31: Caution sous-traitants vs nous | B31: % | C31: 0.05 | D31: 0.05 | E31: 0.05 | F31: 0.05 | G31: 0.05 | H31: Retenue garantie sur ST
A32: BFR & CONDITIONS DE PAIEMENT
A33: Avance de démarrage | B33: % du marché | C33: 0.15 | D33: 0.15 | E33: 0.15 | F33: 0.15 | G33: 0.15 | H33: Versée à la signature
A34: Retenue de garantie | B34: % des décomptes | C34: 0.07 | D34: 0.07 | E34: 0.07 | F34: 0.07 | G34: 0.07 | H34: Retenue sur chaque CP, libérée au DGD
A35: Délai retenue de garantie | B35: mois après réception | C35: 12 | D35: 12 | E35: 12 | F35: 12 | G35: 12 | H35: Délai libération RG
A36: Délai moyen paiement Etat (DSO) | B36: jours | C36: 120 | D36: 110 | E36: 100 | F36: 95 | G36: 90 | H36: Délai de règlement décompte certifié
A37: Délai fournisseurs (DPO) | B37: jours | C37: 60 | D37: 65 | E37: 65 | F37: 70 | G37: 70 | H37: Délai de paiement fournisseurs
A38: Délai paiement ST (DPO-ST) | B38: jours | C38: 75 | D38: 75 | E38: 75 | F38: 75 | G38: 75 | H38: Délai paiement sous-traitants
A39: CAUTIONS BANCAIRES
A40: Caution de soumission | B40: % AO soumis | C40: 0.015 | D40: 0.015 | E40: 0.015 | F40: 0.015 | G40: 0.015 | H40: 1,5% du montant pour les AO
A41: Caution restitution avance | B41: % du marché | C41: 0.15 | D41: 0.15 | E41: 0.15 | F41: 0.15 | G41: 0.15 | H41: Égale à l'avance reçue
A42: Caution de bonne fin | B42: % du marché | C42: 0.05 | D42: 0.05 | E42: 0.05 | F42: 0.05 | G42: 0.05 | H42: Pendant exécution
A43: Caution retenue de garantie | B43: % des décomptes | C43: 0.07 | D43: 0.07 | E43: 0.07 | F43: 0.07 | G43: 0.07 | H43: Remplace la RG cash
A44: Commission caution / an | B44: % | C44: 0.025 | D44: 0.024 | E44: 0.023 | F44: 0.022 | G44: 0.02 | H44: Commission bancaire annuelle
A45: Contre-garantie cash bloquée | B45: % caution | C45: 0.2 | D45: 0.18 | E45: 0.15 | F45: 0.12 | G45: 0.1 | H45: Dépôt bloqué à la banque
A46: PARC MATÉRIEL & ENGINS
A47: Valeur parc matériel initial | B47: FCFA | C47: 4500000000 | D47: 0 | E47: 0 | F47: 0 | G47: 0 | H47: Valeur brute des engins au 01/01
A48: Acquisition matériel / an | B48: FCFA | C48: 800000000 | D48: 1200000000 | E48: 1500000000 | F48: 1500000000 | G48: 1800000000 | H48: CAPEX engins
A49: Durée amortissement engins | B49: années | C49: 7 | D49: 7 | E49: 7 | F49: 7 | G49: 7 | H49: Amort linéaire 7 ans
A50: Coût location engins / mois | B50: FCFA | C50: 95000000 | D50: 110000000 | E50: 125000000 | F50: 140000000 | G50: 155000000 | H50: Location engins externes (location courte)
A51: Carburant & maintenance / an | B51: FCFA | C51: 550000000 | D51: 720000000 | E51: 880000000 | F51: 1020000000 | G51: 1150000000 | H51: OPEX engins propres
A52: Taux d'utilisation engins | B52: % | C52: 0.65 | D52: 0.7 | E52: 0.72 | F52: 0.75 | G52: 0.75 | H52: Heures utiles / heures dispo
A53: MASSE SALARIALE STRUCTURE (HORS PRODUCTION)
A54: ETP Direction & Corporate | B54: nb | C54: 12 | D54: 14 | E54: 16 | F54: 18 | G54: 20 | H54: Direction, juridique, finance, RH
A55: Salaire chargé Direction | B55: FCFA/mois | C55: 2200000 | D55: 2300000 | E55: 2400000 | F55: 2500000 | G55: 2600000 | H55: Salaire chargé moyen
A56: ETP Bureau d'études & ingénierie | B56: nb | C56: 18 | D56: 22 | E56: 26 | F56: 30 | G56: 32 | H56: Métreurs, projeteurs, ingénieurs
A57: Salaire chargé BE | B57: FCFA/mois | C57: 1450000 | D57: 1500000 | E57: 1550000 | F57: 1600000 | G57: 1650000 | H57: Salaire chargé moyen
A58: ETP Encadrement chantiers | B58: nb | C58: 32 | D58: 40 | E58: 48 | F58: 56 | G58: 62 | H58: Conducteurs travaux, chefs chantier
A59: Salaire chargé Encadrement | B59: FCFA/mois | C59: 1250000 | D59: 1300000 | E59: 1350000 | F59: 1400000 | G59: 1450000 | H59: Salaire chargé moyen
A60: ETP Support (compta, achats, QHSE) | B60: nb | C60: 22 | D60: 26 | E60: 30 | F60: 34 | G60: 38 | H60: Fonctions support
A61: Salaire chargé Support | B61: FCFA/mois | C61: 950000 | D61: 1000000 | E61: 1050000 | F61: 1100000 | G61: 1150000 | H61: Salaire chargé moyen
A62: CHARGES FIXES STRUCTURE (HORS PRODUCTION)
A63: Loyer siège & dépôts / mois | B63: FCFA | C63: 22000000 | D63: 24000000 | E63: 26000000 | F63: 28000000 | G63: 30000000 | H63: Siège, ateliers, dépôts
A64: Assurances générales / an | B64: FCFA | C64: 180000000 | D64: 210000000 | E64: 240000000 | F64: 270000000 | G64: 300000000 | H64: RC, dommages-ouvrage, flotte
A65: IT, télécoms, ERP / mois | B65: FCFA | C65: 8500000 | D65: 9500000 | E65: 11000000 | F65: 12500000 | G65: 14000000 | H65: Infogérance, licences, comm
A66: Frais juridiques & honoraires / an | B66: FCFA | C66: 95000000 | D66: 110000000 | E66: 125000000 | F66: 140000000 | G66: 155000000 | H66: Cabinets juridiques, audit, expert
A67: Marketing & relations institutionnelles / an | B67: FCFA | C67: 120000000 | D67: 145000000 | E67: 170000000 | F67: 195000000 | G67: 220000000 | H67: Salons, lobbying, communication
A68: Formation & QHSE / an | B68: FCFA | C68: 65000000 | D68: 75000000 | E68: 90000000 | F68: 105000000 | G68: 120000000 | H68: Habilitations, certifications
A69: Divers & déplacements / mois | B69: FCFA | C69: 12000000 | D69: 14000000 | E69: 16000000 | F69: 18000000 | G69: 20000000 | H69: Missions, hôtels, divers
A70: FINANCEMENT & STRUCTURE FINANCIÈRE
A71: Capitaux propres au 01/01 | B71: FCFA | C71: 6500000000 | D71: 0 | E71: 0 | F71: 0 | G71: 0 | H71: Equity à l'ouverture (cumulé après)
A72: Dette MLT au 01/01 | B72: FCFA | C72: 3500000000 | D72: 0 | E72: 0 | F72: 0 | G72: 0 | H72: Endettement long terme initial
A73: Taux dette MLT | B73: % | C73: 0.085 | D73: 0.085 | E73: 0.082 | F73: 0.08 | G73: 0.078 | H73: Coût dette à terme
A74: Découvert / mobilisation créances | B74: FCFA | C74: 2500000000 | D74: 3500000000 | E74: 4500000000 | F74: 5000000000 | G74: 5500000000 | H74: Ligne court terme disponible
A75: Taux découvert / CT | B75: % | C75: 0.115 | D75: 0.115 | E75: 0.112 | F75: 0.11 | G75: 0.108 | H75: Coût ligne courte
A76: Trésorerie initiale | B76: FCFA | C76: 1800000000 | D76: 0 | E76: 0 | F76: 0 | G76: 0 | H76: Cash disponible au 01/01

Sheet 3. Pipeline & Backlog
A1: PIPELINE COMMERCIAL & CARNET DE COMMANDES (BACKLOG)
A3: Indicateur | B3: Année 1 | C3: Année 2 | D3: Année 3 | E3: Année 4 | F3: Année 5 | H3: Commentaire
A4: ACTIVITÉ COMMERCIALE
A5: AO étudiés | B5: ='2. Hypothèses'!$C$10 -> 28 | C5: ='2. Hypothèses'!$D$10 -> 35 | D5: ='2. Hypothèses'!$E$10 -> 42 | E5: ='2. Hypothèses'!$F$10 -> 48 | F5: ='2. Hypothèses'!$G$10 -> 55 | H5: Appels d'offres soumis
A6: Taux de transformation | B6: ='2. Hypothèses'!$C$11 -> 0.32 | C6: ='2. Hypothèses'!$D$11 -> 0.35 | D6: ='2. Hypothèses'!$E$11 -> 0.38 | E6: ='2. Hypothèses'!$F$11 -> 0.4 | F6: ='2. Hypothèses'!$G$11 -> 0.42 | H6: Hit-rate
A7: Chantiers gagnés / an | B7: =ROUND(B5*B6,0) -> 9 | C7: =ROUND(C5*C6,0) -> 12 | D7: =ROUND(D5*D6,0) -> 16 | E7: =ROUND(E5*E6,0) -> 19 | F7: =ROUND(F5*F6,0) -> 23 | H7: Nb de nouveaux chantiers signés
A8: Valeur moyenne chantier | B8: ='2. Hypothèses'!$C$12 -> 3500000000 | C8: ='2. Hypothèses'!$D$12 -> 4200000000 | D8: ='2. Hypothèses'!$E$12 -> 5000000000 | E8: ='2. Hypothèses'!$F$12 -> 5800000000 | F8: ='2. Hypothèses'!$G$12 -> 6500000000 | H8: Ticket moyen
A9: PRISES DE COMMANDES & BACKLOG
A10: Prises de commandes / an | B10: =B7*B8 -> 31500000000 | C10: =C7*C8 -> 50400000000 | D10: =D7*D8 -> 80000000000 | E10: =E7*E8 -> 110200000000 | F10: =F7*F8 -> 149500000000 | H10: Valeur nouveaux marchés signés
A11: Backlog début de période | B11: ='2. Hypothèses'!$C$14 -> 35000000000 | C11: =B13 -> 5.3721682e+10 | D11: =C13 -> 6.2903732e+10 | E11: =D13 -> 7.8847269e+10 | F11: =E13 -> 9.5417481e+10 | H11: Carnet à l'ouverture
A12: CA reconnu (déversement) | B12: ='4. Portefeuille chantiers'!B23 -> 1.2778318e+10 | C12: ='4. Portefeuille chantiers'!C23 -> 41217950000 | D12: ='4. Portefeuille chantiers'!D23 -> 6.4056463e+10 | E12: ='4. Portefeuille chantiers'!E23 -> 9.3629787e+10 | F12: ='4. Portefeuille chantiers'!F23 -> 1.2671817e+11 | H12: CA reconnu à l'avancement
A13: Backlog fin de période | B13: =B11+B10-B12 -> 5.3721682e+10 | C13: =C11+C10-C12 -> 6.2903732e+10 | D13: =D11+D10-D12 -> 7.8847269e+10 | E13: =E11+E10-E12 -> 9.5417481e+10 | F13: =F11+F10-F12 -> 1.1819931e+11 | H13: Carnet de commandes à la clôture
A14: INDICATEURS PIPELINE
A15: Book-to-bill ratio | B15: =IFERROR(B10/B12,0) -> 2.4651131 | C15: =IFERROR(C10/C12,0) -> 1.2227682 | D15: =IFERROR(D10/D12,0) -> 1.2488982 | E15: =IFERROR(E10/E12,0) -> 1.1769759 | F15: =IFERROR(F10/F12,0) -> 1.1797835 | H15: Prises / CA reconnu (>1 = croissance)
A16: Couverture backlog (mois) | B16: =IFERROR(B13/(B12/12),0) -> 50.449533 | C16: =IFERROR(C13/(C12/12),0) -> 18.313496 | D16: =IFERROR(D13/(D12/12),0) -> 14.770832 | E16: =IFERROR(E13/(E12/12),0) -> 12.229119 | F16: =IFERROR(F13/(F12/12),0) -> 11.193279 | H16: Backlog / (CA / 12)
A17: Coût commercial total / an | B17: ='2. Hypothèses'!$C$15*'2. Hypothèses'!$C$10 -> 126000000 | C17: ='2. Hypothèses'!$D$15*'2. Hypothèses'!$D$10 -> 168000000 | D17: ='2. Hypothèses'!$E$15*'2. Hypothèses'!$E$10 -> 218400000 | E17: ='2. Hypothèses'!$F$15*'2. Hypothèses'!$F$10 -> 264000000 | F17: ='2. Hypothèses'!$G$15*'2. Hypothèses'!$G$10 -> 319000000 | H17: Coût bureau d'études d'offres
A18: Coût d'acquisition par chantier | B18: =IFERROR(B17/B7,0) -> 14000000 | C18: =IFERROR(C17/C7,0) -> 14000000 | D18: =IFERROR(D17/D7,0) -> 13650000 | E18: =IFERROR(E17/E7,0) -> 13894737 | F18: =IFERROR(F17/F7,0) -> 13869565 | H18: Coût AO / nb chantiers gagnés

Sheet 4. Portefeuille chantiers
A1: PORTEFEUILLE DES CHANTIERS — VUE PROJET
A3: Code | B3: Désignation | C3: Type | D3: Mois démarrage | E3: Durée (mois) | F3: Valeur (FCFA) | G3: M01 | H3: M02 | I3: M03 | J3: M04 | K3: M05 | L3: M06 | M3: M07 | N3: M08 | O3: M09 | P3: M10 | Q3: M11 | R3: M12 | S3: M13 | T3: M14 | U3: M15 | V3: M16 | W3: M17 | X3: M18 | Y3: M19 | Z3: M20 | AA3: M21 | AB3: M22 | AC3: M23 | AD3: M24 | AE3: M25 | AF3: M26 | AG3: M27 | AH3: M28 | AI3: M29 | AJ3: M30 | AK3: M31 | AL3: M32 | AM3: M33 | AN3: M34 | AO3: M35 | AP3: M36 | AQ3: M37 | AR3: M38 | AS3: M39 | AT3: M40 | AU3: M41 | AV3: M42 | AW3: M43 | AX3: M44 | AY3: M45 | AZ3: M46 | BA3: M47 | BB3: M48 | BC3: M49 | BD3: M50 | BE3: M51 | BF3: M52 | BG3: M53 | BH3: M54 | BI3: M55 | BJ3: M56 | BK3: M57 | BL3: M58 | BM3: M59 | BN3: M60
A4: CH-01 | B4: Logements sociaux Phase 1 | C4: Bâtiment public | D4: 1 | E4: 18 | F4: 4200000000 | G4: =IF(AND(1>=$D$4,1<=$D$4+$E$4-1),$F$4/$E$4,0) -> 2.3333333e+08 | H4: =IF(AND(2>=$D$4,2<=$D$4+$E$4-1),$F$4/$E$4,0) -> 2.3333333e+08 | I4: =IF(AND(3>=$D$4,3<=$D$4+$E$4-1),$F$4/$E$4,0) -> 2.3333333e+08 | J4: =IF(AND(4>=$D$4,4<=$D$4+$E$4-1),$F$4/$E$4,0) -> 2.3333333e+08 | K4: =IF(AND(5>=$D$4,5<=$D$4+$E$4-1),$F$4/$E$4,0) -> 2.3333333e+08 | L4: =IF(AND(6>=$D$4,6<=$D$4+$E$4-1),$F$4/$E$4,0) -> 2.3333333e+08 | M4: =IF(AND(7>=$D$4,7<=$D$4+$E$4-1),$F$4/$E$4,0) -> 2.3333333e+08 | N4: =IF(AND(8>=$D$4,8<=$D$4+$E$4-1),$F$4/$E$4,0) -> 2.3333333e+08 | O4: =IF(AND(9>=$D$4,9<=$D$4+$E$4-1),$F$4/$E$4,0) -> 2.3333333e+08 | P4: =IF(AND(10>=$D$4,10<=$D$4+$E$4-1),$F$4/$E$4,0) -> 2.3333333e+08 | Q4: =IF(AND(11>=$D$4,11<=$D$4+$E$4-1),$F$4/$E$4,0) -> 2.3333333e+08 | R4: =IF(AND(12>=$D$4,12<=$D$4+$E$4-1),$F$4/$E$4,0) -> 2.3333333e+08 | S4: =IF(AND(13>=$D$4,13<=$D$4+$E$4-1),$F$4/$E$4,0) -> 2.3333333e+08 | T4: =IF(AND(14>=$D$4,14<=$D$4+$E$4-1),$F$4/$E$4,0) -> 2.3333333e+08 | U4: =IF(AND(15>=$D$4,15<=$D$4+$E$4-1),$F$4/$E$4,0) -> 2.3333333e+08 | V4: =IF(AND(16>=$D$4,16<=$D$4+$E$4-1),$F$4/$E$4,0) -> 2.3333333e+08 | W4: =IF(AND(17>=$D$4,17<=$D$4+$E$4-1),$F$4/$E$4,0) -> 2.3333333e+08 | X4: =IF(AND(18>=$D$4,18<=$D$4+$E$4-1),$F$4/$E$4,0) -> 2.3333333e+08 | Y4: =IF(AND(19>=$D$4,19<=$D$4+$E$4-1),$F$4/$E$4,0) -> 0 | Z4: =IF(AND(20>=$D$4,20<=$D$4+$E$4-1),$F$4/$E$4,0) -> 0 | AA4: =IF(AND(21>=$D$4,21<=$D$4+$E$4-1),$F$4/$E$4,0) -> 0 | AB4: =IF(AND(22>=$D$4,22<=$D$4+$E$4-1),$F$4/$E$4,0) -> 0 | AC4: =IF(AND(23>=$D$4,23<=$D$4+$E$4-1),$F$4/$E$4,0) -> 0 | AD4: =IF(AND(24>=$D$4,24<=$D$4+$E$4-1),$F$4/$E$4,0) -> 0 | AE4: =IF(AND(25>=$D$4,25<=$D$4+$E$4-1),$F$4/$E$4,0) -> 0 | AF4: =IF(AND(26>=$D$4,26<=$D$4+$E$4-1),$F$4/$E$4,0) -> 0 | AG4: =IF(AND(27>=$D$4,27<=$D$4+$E$4-1),$F$4/$E$4,0) -> 0 | AH4: =IF(AND(28>=$D$4,28<=$D$4+$E$4-1),$F$4/$E$4,0) -> 0 | AI4: =IF(AND(29>=$D$4,29<=$D$4+$E$4-1),$F$4/$E$4,0) -> 0 | AJ4: =IF(AND(30>=$D$4,30<=$D$4+$E$4-1),$F$4/$E$4,0) -> 0 | AK4: =IF(AND(31>=$D$4,31<=$D$4+$E$4-1),$F$4/$E$4,0) -> 0 | AL4: =IF(AND(32>=$D$4,32<=$D$4+$E$4-1),$F$4/$E$4,0) -> 0 | AM4: =IF(AND(33>=$D$4,33<=$D$4+$E$4-1),$F$4/$E$4,0) -> 0 | AN4: =IF(AND(34>=$D$4,34<=$D$4+$E$4-1),$F$4/$E$4,0) -> 0 | AO4: =IF(AND(35>=$D$4,35<=$D$4+$E$4-1),$F$4/$E$4,0) -> 0 | AP4: =IF(AND(36>=$D$4,36<=$D$4+$E$4-1),$F$4/$E$4,0) -> 0 | AQ4: =IF(AND(37>=$D$4,37<=$D$4+$E$4-1),$F$4/$E$4,0) -> 0 | AR4: =IF(AND(38>=$D$4,38<=$D$4+$E$4-1),$F$4/$E$4,0) -> 0 | AS4: =IF(AND(39>=$D$4,39<=$D$4+$E$4-1),$F$4/$E$4,0) -> 0 | AT4: =IF(AND(40>=$D$4,40<=$D$4+$E$4-1),$F$4/$E$4,0) -> 0 | AU4: =IF(AND(41>=$D$4,41<=$D$4+$E$4-1),$F$4/$E$4,0) -> 0 | AV4: =IF(AND(42>=$D$4,42<=$D$4+$E$4-1),$F$4/$E$4,0) -> 0 | AW4: =IF(AND(43>=$D$4,43<=$D$4+$E$4-1),$F$4/$E$4,0) -> 0 | AX4: =IF(AND(44>=$D$4,44<=$D$4+$E$4-1),$F$4/$E$4,0) -> 0 | AY4: =IF(AND(45>=$D$4,45<=$D$4+$E$4-1),$F$4/$E$4,0) -> 0 | AZ4: =IF(AND(46>=$D$4,46<=$D$4+$E$4-1),$F$4/$E$4,0) -> 0 | BA4: =IF(AND(47>=$D$4,47<=$D$4+$E$4-1),$F$4/$E$4,0) -> 0 | BB4: =IF(AND(48>=$D$4,48<=$D$4+$E$4-1),$F$4/$E$4,0) -> 0 | BC4: =IF(AND(49>=$D$4,49<=$D$4+$E$4-1),$F$4/$E$4,0) -> 0 | BD4: =IF(AND(50>=$D$4,50<=$D$4+$E$4-1),$F$4/$E$4,0) -> 0 | BE4: =IF(AND(51>=$D$4,51<=$D$4+$E$4-1),$F$4/$E$4,0) -> 0 | BF4: =IF(AND(52>=$D$4,52<=$D$4+$E$4-1),$F$4/$E$4,0) -> 0 | BG4: =IF(AND(53>=$D$4,53<=$D$4+$E$4-1),$F$4/$E$4,0) -> 0 | BH4: =IF(AND(54>=$D$4,54<=$D$4+$E$4-1),$F$4/$E$4,0) -> 0 | BI4: =IF(AND(55>=$D$4,55<=$D$4+$E$4-1),$F$4/$E$4,0) -> 0 | BJ4: =IF(AND(56>=$D$4,56<=$D$4+$E$4-1),$F$4/$E$4,0) -> 0 | BK4: =IF(AND(57>=$D$4,57<=$D$4+$E$4-1),$F$4/$E$4,0) -> 0 | BL4: =IF(AND(58>=$D$4,58<=$D$4+$E$4-1),$F$4/$E$4,0) -> 0 | BM4: =IF(AND(59>=$D$4,59<=$D$4+$E$4-1),$F$4/$E$4,0) -> 0 | BN4: =IF(AND(60>=$D$4,60<=$D$4+$E$4-1),$F$4/$E$4,0) -> 0
A5: CH-02 | B5: Centre administratif régional | C5: Tertiaire public | D5: 1 | E5: 22 | F5: 6500000000 | G5: =IF(AND(1>=$D$5,1<=$D$5+$E$5-1),$F$5/$E$5,0) -> 2.9545455e+08 | H5: =IF(AND(2>=$D$5,2<=$D$5+$E$5-1),$F$5/$E$5,0) -> 2.9545455e+08 | I5: =IF(AND(3>=$D$5,3<=$D$5+$E$5-1),$F$5/$E$5,0) -> 2.9545455e+08 | J5: =IF(AND(4>=$D$5,4<=$D$5+$E$5-1),$F$5/$E$5,0) -> 2.9545455e+08 | K5: =IF(AND(5>=$D$5,5<=$D$5+$E$5-1),$F$5/$E$5,0) -> 2.9545455e+08 | L5: =IF(AND(6>=$D$5,6<=$D$5+$E$5-1),$F$5/$E$5,0) -> 2.9545455e+08 | M5: =IF(AND(7>=$D$5,7<=$D$5+$E$5-1),$F$5/$E$5,0) -> 2.9545455e+08 | N5: =IF(AND(8>=$D$5,8<=$D$5+$E$5-1),$F$5/$E$5,0) -> 2.9545455e+08 | O5: =IF(AND(9>=$D$5,9<=$D$5+$E$5-1),$F$5/$E$5,0) -> 2.9545455e+08 | P5: =IF(AND(10>=$D$5,10<=$D$5+$E$5-1),$F$5/$E$5,0) -> 2.9545455e+08 | Q5: =IF(AND(11>=$D$5,11<=$D$5+$E$5-1),$F$5/$E$5,0) -> 2.9545455e+08 | R5: =IF(AND(12>=$D$5,12<=$D$5+$E$5-1),$F$5/$E$5,0) -> 2.9545455e+08 | S5: =IF(AND(13>=$D$5,13<=$D$5+$E$5-1),$F$5/$E$5,0) -> 2.9545455e+08 | T5: =IF(AND(14>=$D$5,14<=$D$5+$E$5-1),$F$5/$E$5,0) -> 2.9545455e+08 | U5: =IF(AND(15>=$D$5,15<=$D$5+$E$5-1),$F$5/$E$5,0) -> 2.9545455e+08 | V5: =IF(AND(16>=$D$5,16<=$D$5+$E$5-1),$F$5/$E$5,0) -> 2.9545455e+08 | W5: =IF(AND(17>=$D$5,17<=$D$5+$E$5-1),$F$5/$E$5,0) -> 2.9545455e+08 | X5: =IF(AND(18>=$D$5,18<=$D$5+$E$5-1),$F$5/$E$5,0) -> 2.9545455e+08 | Y5: =IF(AND(19>=$D$5,19<=$D$5+$E$5-1),$F$5/$E$5,0) -> 2.9545455e+08 | Z5: =IF(AND(20>=$D$5,20<=$D$5+$E$5-1),$F$5/$E$5,0) -> 2.9545455e+08 | AA5: =IF(AND(21>=$D$5,21<=$D$5+$E$5-1),$F$5/$E$5,0) -> 2.9545455e+08 | AB5: =IF(AND(22>=$D$5,22<=$D$5+$E$5-1),$F$5/$E$5,0) -> 2.9545455e+08 | AC5: =IF(AND(23>=$D$5,23<=$D$5+$E$5-1),$F$5/$E$5,0) -> 0 | AD5: =IF(AND(24>=$D$5,24<=$D$5+$E$5-1),$F$5/$E$5,0) -> 0 | AE5: =IF(AND(25>=$D$5,25<=$D$5+$E$5-1),$F$5/$E$5,0) -> 0 | AF5: =IF(AND(26>=$D$5,26<=$D$5+$E$5-1),$F$5/$E$5,0) -> 0 | AG5: =IF(AND(27>=$D$5,27<=$D$5+$E$5-1),$F$5/$E$5,0) -> 0 | AH5: =IF(AND(28>=$D$5,28<=$D$5+$E$5-1),$F$5/$E$5,0) -> 0 | AI5: =IF(AND(29>=$D$5,29<=$D$5+$E$5-1),$F$5/$E$5,0) -> 0 | AJ5: =IF(AND(30>=$D$5,30<=$D$5+$E$5-1),$F$5/$E$5,0) -> 0 | AK5: =IF(AND(31>=$D$5,31<=$D$5+$E$5-1),$F$5/$E$5,0) -> 0 | AL5: =IF(AND(32>=$D$5,32<=$D$5+$E$5-1),$F$5/$E$5,0) -> 0 | AM5: =IF(AND(33>=$D$5,33<=$D$5+$E$5-1),$F$5/$E$5,0) -> 0 | AN5: =IF(AND(34>=$D$5,34<=$D$5+$E$5-1),$F$5/$E$5,0) -> 0 | AO5: =IF(AND(35>=$D$5,35<=$D$5+$E$5-1),$F$5/$E$5,0) -> 0 | AP5: =IF(AND(36>=$D$5,36<=$D$5+$E$5-1),$F$5/$E$5,0) -> 0 | AQ5: =IF(AND(37>=$D$5,37<=$D$5+$E$5-1),$F$5/$E$5,0) -> 0 | AR5: =IF(AND(38>=$D$5,38<=$D$5+$E$5-1),$F$5/$E$5,0) -> 0 | AS5: =IF(AND(39>=$D$5,39<=$D$5+$E$5-1),$F$5/$E$5,0) -> 0 | AT5: =IF(AND(40>=$D$5,40<=$D$5+$E$5-1),$F$5/$E$5,0) -> 0 | AU5: =IF(AND(41>=$D$5,41<=$D$5+$E$5-1),$F$5/$E$5,0) -> 0 | AV5: =IF(AND(42>=$D$5,42<=$D$5+$E$5-1),$F$5/$E$5,0) -> 0 | AW5: =IF(AND(43>=$D$5,43<=$D$5+$E$5-1),$F$5/$E$5,0) -> 0 | AX5: =IF(AND(44>=$D$5,44<=$D$5+$E$5-1),$F$5/$E$5,0) -> 0 | AY5: =IF(AND(45>=$D$5,45<=$D$5+$E$5-1),$F$5/$E$5,0) -> 0 | AZ5: =IF(AND(46>=$D$5,46<=$D$5+$E$5-1),$F$5/$E$5,0) -> 0 | BA5: =IF(AND(47>=$D$5,47<=$D$5+$E$5-1),$F$5/$E$5,0) -> 0 | BB5: =IF(AND(48>=$D$5,48<=$D$5+$E$5-1),$F$5/$E$5,0) -> 0 | BC5: =IF(AND(49>=$D$5,49<=$D$5+$E$5-1),$F$5/$E$5,0) -> 0 | BD5: =IF(AND(50>=$D$5,50<=$D$5+$E$5-1),$F$5/$E$5,0) -> 0 | BE5: =IF(AND(51>=$D$5,51<=$D$5+$E$5-1),$F$5/$E$5,0) -> 0 | BF5: =IF(AND(52>=$D$5,52<=$D$5+$E$5-1),$F$5/$E$5,0) -> 0 | BG5: =IF(AND(53>=$D$5,53<=$D$5+$E$5-1),$F$5/$E$5,0) -> 0 | BH5: =IF(AND(54>=$D$5,54<=$D$5+$E$5-1),$F$5/$E$5,0) -> 0 | BI5: =IF(AND(55>=$D$5,55<=$D$5+$E$5-1),$F$5/$E$5,0) -> 0 | BJ5: =IF(AND(56>=$D$5,56<=$D$5+$E$5-1),$F$5/$E$5,0) -> 0 | BK5: =IF(AND(57>=$D$5,57<=$D$5+$E$5-1),$F$5/$E$5,0) -> 0 | BL5: =IF(AND(58>=$D$5,58<=$D$5+$E$5-1),$F$5/$E$5,0) -> 0 | BM5: =IF(AND(59>=$D$5,59<=$D$5+$E$5-1),$F$5/$E$5,0) -> 0 | BN5: =IF(AND(60>=$D$5,60<=$D$5+$E$5-1),$F$5/$E$5,0) -> 0
A6: CH-03 | B6: Lycée technique national | C6: Public | D6: 3 | E6: 20 | F6: 3800000000 | G6: =IF(AND(1>=$D$6,1<=$D$6+$E$6-1),$F$6/$E$6,0) -> 0 | H6: =IF(AND(2>=$D$6,2<=$D$6+$E$6-1),$F$6/$E$6,0) -> 0 | I6: =IF(AND(3>=$D$6,3<=$D$6+$E$6-1),$F$6/$E$6,0) -> 190000000 | J6: =IF(AND(4>=$D$6,4<=$D$6+$E$6-1),$F$6/$E$6,0) -> 190000000 | K6: =IF(AND(5>=$D$6,5<=$D$6+$E$6-1),$F$6/$E$6,0) -> 190000000 | L6: =IF(AND(6>=$D$6,6<=$D$6+$E$6-1),$F$6/$E$6,0) -> 190000000 | M6: =IF(AND(7>=$D$6,7<=$D$6+$E$6-1),$F$6/$E$6,0) -> 190000000 | N6: =IF(AND(8>=$D$6,8<=$D$6+$E$6-1),$F$6/$E$6,0) -> 190000000 | O6: =IF(AND(9>=$D$6,9<=$D$6+$E$6-1),$F$6/$E$6,0) -> 190000000 | P6: =IF(AND(10>=$D$6,10<=$D$6+$E$6-1),$F$6/$E$6,0) -> 190000000 | Q6: =IF(AND(11>=$D$6,11<=$D$6+$E$6-1),$F$6/$E$6,0) -> 190000000 | R6: =IF(AND(12>=$D$6,12<=$D$6+$E$6-1),$F$6/$E$6,0) -> 190000000 | S6: =IF(AND(13>=$D$6,13<=$D$6+$E$6-1),$F$6/$E$6,0) -> 190000000 | T6: =IF(AND(14>=$D$6,14<=$D$6+$E$6-1),$F$6/$E$6,0) -> 190000000 | U6: =IF(AND(15>=$D$6,15<=$D$6+$E$6-1),$F$6/$E$6,0) -> 190000000 | V6: =IF(AND(16>=$D$6,16<=$D$6+$E$6-1),$F$6/$E$6,0) -> 190000000 | W6: =IF(AND(17>=$D$6,17<=$D$6+$E$6-1),$F$6/$E$6,0) -> 190000000 | X6: =IF(AND(18>=$D$6,18<=$D$6+$E$6-1),$F$6/$E$6,0) -> 190000000 | Y6: =IF(AND(19>=$D$6,19<=$D$6+$E$6-1),$F$6/$E$6,0) -> 190000000 | Z6: =IF(AND(20>=$D$6,20<=$D$6+$E$6-1),$F$6/$E$6,0) -> 190000000 | AA6: =IF(AND(21>=$D$6,21<=$D$6+$E$6-1),$F$6/$E$6,0) -> 190000000 | AB6: =IF(AND(22>=$D$6,22<=$D$6+$E$6-1),$F$6/$E$6,0) -> 190000000 | AC6: =IF(AND(23>=$D$6,23<=$D$6+$E$6-1),$F$6/$E$6,0) -> 0 | AD6: =IF(AND(24>=$D$6,24<=$D$6+$E$6-1),$F$6/$E$6,0) -> 0 | AE6: =IF(AND(25>=$D$6,25<=$D$6+$E$6-1),$F$6/$E$6,0) -> 0 | AF6: =IF(AND(26>=$D$6,26<=$D$6+$E$6-1),$F$6/$E$6,0) -> 0 | AG6: =IF(AND(27>=$D$6,27<=$D$6+$E$6-1),$F$6/$E$6,0) -> 0 | AH6: =IF(AND(28>=$D$6,28<=$D$6+$E$6-1),$F$6/$E$6,0) -> 0 | AI6: =IF(AND(29>=$D$6,29<=$D$6+$E$6-1),$F$6/$E$6,0) -> 0 | AJ6: =IF(AND(30>=$D$6,30<=$D$6+$E$6-1),$F$6/$E$6,0) -> 0 | AK6: =IF(AND(31>=$D$6,31<=$D$6+$E$6-1),$F$6/$E$6,0) -> 0 | AL6: =IF(AND(32>=$D$6,32<=$D$6+$E$6-1),$F$6/$E$6,0) -> 0 | AM6: =IF(AND(33>=$D$6,33<=$D$6+$E$6-1),$F$6/$E$6,0) -> 0 | AN6: =IF(AND(34>=$D$6,34<=$D$6+$E$6-1),$F$6/$E$6,0) -> 0 | AO6: =IF(AND(35>=$D$6,35<=$D$6+$E$6-1),$F$6/$E$6,0) -> 0 | AP6: =IF(AND(36>=$D$6,36<=$D$6+$E$6-1),$F$6/$E$6,0) -> 0 | AQ6: =IF(AND(37>=$D$6,37<=$D$6+$E$6-1),$F$6/$E$6,0) -> 0 | AR6: =IF(AND(38>=$D$6,38<=$D$6+$E$6-1),$F$6/$E$6,0) -> 0 | AS6: =IF(AND(39>=$D$6,39<=$D$6+$E$6-1),$F$6/$E$6,0) -> 0 | AT6: =IF(AND(40>=$D$6,40<=$D$6+$E$6-1),$F$6/$E$6,0) -> 0 | AU6: =IF(AND(41>=$D$6,41<=$D$6+$E$6-1),$F$6/$E$6,0) -> 0 | AV6: =IF(AND(42>=$D$6,42<=$D$6+$E$6-1),$F$6/$E$6,0) -> 0 | AW6: =IF(AND(43>=$D$6,43<=$D$6+$E$6-1),$F$6/$E$6,0) -> 0 | AX6: =IF(AND(44>=$D$6,44<=$D$6+$E$6-1),$F$6/$E$6,0) -> 0 | AY6: =IF(AND(45>=$D$6,45<=$D$6+$E$6-1),$F$6/$E$6,0) -> 0 | AZ6: =IF(AND(46>=$D$6,46<=$D$6+$E$6-1),$F$6/$E$6,0) -> 0 | BA6: =IF(AND(47>=$D$6,47<=$D$6+$E$6-1),$F$6/$E$6,0) -> 0 | BB6: =IF(AND(48>=$D$6,48<=$D$6+$E$6-1),$F$6/$E$6,0) -> 0 | BC6: =IF(AND(49>=$D$6,49<=$D$6+$E$6-1),$F$6/$E$6,0) -> 0 | BD6: =IF(AND(50>=$D$6,50<=$D$6+$E$6-1),$F$6/$E$6,0) -> 0 | BE6: =IF(AND(51>=$D$6,51<=$D$6+$E$6-1),$F$6/$E$6,0) -> 0 | BF6: =IF(AND(52>=$D$6,52<=$D$6+$E$6-1),$F$6/$E$6,0) -> 0 | BG6: =IF(AND(53>=$D$6,53<=$D$6+$E$6-1),$F$6/$E$6,0) -> 0 | BH6: =IF(AND(54>=$D$6,54<=$D$6+$E$6-1),$F$6/$E$6,0) -> 0 | BI6: =IF(AND(55>=$D$6,55<=$D$6+$E$6-1),$F$6/$E$6,0) -> 0 | BJ6: =IF(AND(56>=$D$6,56<=$D$6+$E$6-1),$F$6/$E$6,0) -> 0 | BK6: =IF(AND(57>=$D$6,57<=$D$6+$E$6-1),$F$6/$E$6,0) -> 0 | BL6: =IF(AND(58>=$D$6,58<=$D$6+$E$6-1),$F$6/$E$6,0) -> 0 | BM6: =IF(AND(59>=$D$6,59<=$D$6+$E$6-1),$F$6/$E$6,0) -> 0 | BN6: =IF(AND(60>=$D$6,60<=$D$6+$E$6-1),$F$6/$E$6,0) -> 0
A7: CH-04 | B7: Hôpital de district | C7: Santé publique | D7: 5 | E7: 24 | F7: 5500000000 | G7: =IF(AND(1>=$D$7,1<=$D$7+$E$7-1),$F$7/$E$7,0) -> 0 | H7: =IF(AND(2>=$D$7,2<=$D$7+$E$7-1),$F$7/$E$7,0) -> 0 | I7: =IF(AND(3>=$D$7,3<=$D$7+$E$7-1),$F$7/$E$7,0) -> 0 | J7: =IF(AND(4>=$D$7,4<=$D$7+$E$7-1),$F$7/$E$7,0) -> 0 | K7: =IF(AND(5>=$D$7,5<=$D$7+$E$7-1),$F$7/$E$7,0) -> 2.2916667e+08 | L7: =IF(AND(6>=$D$7,6<=$D$7+$E$7-1),$F$7/$E$7,0) -> 2.2916667e+08 | M7: =IF(AND(7>=$D$7,7<=$D$7+$E$7-1),$F$7/$E$7,0) -> 2.2916667e+08 | N7: =IF(AND(8>=$D$7,8<=$D$7+$E$7-1),$F$7/$E$7,0) -> 2.2916667e+08 | O7: =IF(AND(9>=$D$7,9<=$D$7+$E$7-1),$F$7/$E$7,0) -> 2.2916667e+08 | P7: =IF(AND(10>=$D$7,10<=$D$7+$E$7-1),$F$7/$E$7,0) -> 2.2916667e+08 | Q7: =IF(AND(11>=$D$7,11<=$D$7+$E$7-1),$F$7/$E$7,0) -> 2.2916667e+08 | R7: =IF(AND(12>=$D$7,12<=$D$7+$E$7-1),$F$7/$E$7,0) -> 2.2916667e+08 | S7: =IF(AND(13>=$D$7,13<=$D$7+$E$7-1),$F$7/$E$7,0) -> 2.2916667e+08 | T7: =IF(AND(14>=$D$7,14<=$D$7+$E$7-1),$F$7/$E$7,0) -> 2.2916667e+08 | U7: =IF(AND(15>=$D$7,15<=$D$7+$E$7-1),$F$7/$E$7,0) -> 2.2916667e+08 | V7: =IF(AND(16>=$D$7,16<=$D$7+$E$7-1),$F$7/$E$7,0) -> 2.2916667e+08 | W7: =IF(AND(17>=$D$7,17<=$D$7+$E$7-1),$F$7/$E$7,0) -> 2.2916667e+08 | X7: =IF(AND(18>=$D$7,18<=$D$7+$E$7-1),$F$7/$E$7,0) -> 2.2916667e+08 | Y7: =IF(AND(19>=$D$7,19<=$D$7+$E$7-1),$F$7/$E$7,0) -> 2.2916667e+08 | Z7: =IF(AND(20>=$D$7,20<=$D$7+$E$7-1),$F$7/$E$7,0) -> 2.2916667e+08 | AA7: =IF(AND(21>=$D$7,21<=$D$7+$E$7-1),$F$7/$E$7,0) -> 2.2916667e+08 | AB7: =IF(AND(22>=$D$7,22<=$D$7+$E$7-1),$F$7/$E$7,0) -> 2.2916667e+08 | AC7: =IF(AND(23>=$D$7,23<=$D$7+$E$7-1),$F$7/$E$7,0) -> 2.2916667e+08 | AD7: =IF(AND(24>=$D$7,24<=$D$7+$E$7-1),$F$7/$E$7,0) -> 2.2916667e+08 | AE7: =IF(AND(25>=$D$7,25<=$D$7+$E$7-1),$F$7/$E$7,0) -> 2.2916667e+08 | AF7: =IF(AND(26>=$D$7,26<=$D$7+$E$7-1),$F$7/$E$7,0) -> 2.2916667e+08 | AG7: =IF(AND(27>=$D$7,27<=$D$7+$E$7-1),$F$7/$E$7,0) -> 2.2916667e+08 | AH7: =IF(AND(28>=$D$7,28<=$D$7+$E$7-1),$F$7/$E$7,0) -> 2.2916667e+08 | AI7: =IF(AND(29>=$D$7,29<=$D$7+$E$7-1),$F$7/$E$7,0) -> 0 | AJ7: =IF(AND(30>=$D$7,30<=$D$7+$E$7-1),$F$7/$E$7,0) -> 0 | AK7: =IF(AND(31>=$D$7,31<=$D$7+$E$7-1),$F$7/$E$7,0) -> 0 | AL7: =IF(AND(32>=$D$7,32<=$D$7+$E$7-1),$F$7/$E$7,0) -> 0 | AM7: =IF(AND(33>=$D$7,33<=$D$7+$E$7-1),$F$7/$E$7,0) -> 0 | AN7: =IF(AND(34>=$D$7,34<=$D$7+$E$7-1),$F$7/$E$7,0) -> 0 | AO7: =IF(AND(35>=$D$7,35<=$D$7+$E$7-1),$F$7/$E$7,0) -> 0 | AP7: =IF(AND(36>=$D$7,36<=$D$7+$E$7-1),$F$7/$E$7,0) -> 0 | AQ7: =IF(AND(37>=$D$7,37<=$D$7+$E$7-1),$F$7/$E$7,0) -> 0 | AR7: =IF(AND(38>=$D$7,38<=$D$7+$E$7-1),$F$7/$E$7,0) -> 0 | AS7: =IF(AND(39>=$D$7,39<=$D$7+$E$7-1),$F$7/$E$7,0) -> 0 | AT7: =IF(AND(40>=$D$7,40<=$D$7+$E$7-1),$F$7/$E$7,0) -> 0 | AU7: =IF(AND(41>=$D$7,41<=$D$7+$E$7-1),$F$7/$E$7,0) -> 0 | AV7: =IF(AND(42>=$D$7,42<=$D$7+$E$7-1),$F$7/$E$7,0) -> 0 | AW7: =IF(AND(43>=$D$7,43<=$D$7+$E$7-1),$F$7/$E$7,0) -> 0 | AX7: =IF(AND(44>=$D$7,44<=$D$7+$E$7-1),$F$7/$E$7,0) -> 0 | AY7: =IF(AND(45>=$D$7,45<=$D$7+$E$7-1),$F$7/$E$7,0) -> 0 | AZ7: =IF(AND(46>=$D$7,46<=$D$7+$E$7-1),$F$7/$E$7,0) -> 0 | BA7: =IF(AND(47>=$D$7,47<=$D$7+$E$7-1),$F$7/$E$7,0) -> 0 | BB7: =IF(AND(48>=$D$7,48<=$D$7+$E$7-1),$F$7/$E$7,0) -> 0 | BC7: =IF(AND(49>=$D$7,49<=$D$7+$E$7-1),$F$7/$E$7,0) -> 0 | BD7: =IF(AND(50>=$D$7,50<=$D$7+$E$7-1),$F$7/$E$7,0) -> 0 | BE7: =IF(AND(51>=$D$7,51<=$D$7+$E$7-1),$F$7/$E$7,0) -> 0 | BF7: =IF(AND(52>=$D$7,52<=$D$7+$E$7-1),$F$7/$E$7,0) -> 0 | BG7: =IF(AND(53>=$D$7,53<=$D$7+$E$7-1),$F$7/$E$7,0) -> 0 | BH7: =IF(AND(54>=$D$7,54<=$D$7+$E$7-1),$F$7/$E$7,0) -> 0 | BI7: =IF(AND(55>=$D$7,55<=$D$7+$E$7-1),$F$7/$E$7,0) -> 0 | BJ7: =IF(AND(56>=$D$7,56<=$D$7+$E$7-1),$F$7/$E$7,0) -> 0 | BK7: =IF(AND(57>=$D$7,57<=$D$7+$E$7-1),$F$7/$E$7,0) -> 0 | BL7: =IF(AND(58>=$D$7,58<=$D$7+$E$7-1),$F$7/$E$7,0) -> 0 | BM7: =IF(AND(59>=$D$7,59<=$D$7+$E$7-1),$F$7/$E$7,0) -> 0 | BN7: =IF(AND(60>=$D$7,60<=$D$7+$E$7-1),$F$7/$E$7,0) -> 0
A8: CH-05 | B8: Siège institution financière | C8: Tertiaire | D8: 8 | E8: 22 | F8: 4800000000 | G8: =IF(AND(1>=$D$8,1<=$D$8+$E$8-1),$F$8/$E$8,0) -> 0 | H8: =IF(AND(2>=$D$8,2<=$D$8+$E$8-1),$F$8/$E$8,0) -> 0 | I8: =IF(AND(3>=$D$8,3<=$D$8+$E$8-1),$F$8/$E$8,0) -> 0 | J8: =IF(AND(4>=$D$8,4<=$D$8+$E$8-1),$F$8/$E$8,0) -> 0 | K8: =IF(AND(5>=$D$8,5<=$D$8+$E$8-1),$F$8/$E$8,0) -> 0 | L8: =IF(AND(6>=$D$8,6<=$D$8+$E$8-1),$F$8/$E$8,0) -> 0 | M8: =IF(AND(7>=$D$8,7<=$D$8+$E$8-1),$F$8/$E$8,0) -> 0 | N8: =IF(AND(8>=$D$8,8<=$D$8+$E$8-1),$F$8/$E$8,0) -> 2.1818182e+08 | O8: =IF(AND(9>=$D$8,9<=$D$8+$E$8-1),$F$8/$E$8,0) -> 2.1818182e+08 | P8: =IF(AND(10>=$D$8,10<=$D$8+$E$8-1),$F$8/$E$8,0) -> 2.1818182e+08 | Q8: =IF(AND(11>=$D$8,11<=$D$8+$E$8-1),$F$8/$E$8,0) -> 2.1818182e+08 | R8: =IF(AND(12>=$D$8,12<=$D$8+$E$8-1),$F$8/$E$8,0) -> 2.1818182e+08 | S8: =IF(AND(13>=$D$8,13<=$D$8+$E$8-1),$F$8/$E$8,0) -> 2.1818182e+08 | T8: =IF(AND(14>=$D$8,14<=$D$8+$E$8-1),$F$8/$E$8,0) -> 2.1818182e+08 | U8: =IF(AND(15>=$D$8,15<=$D$8+$E$8-1),$F$8/$E$8,0) -> 2.1818182e+08 | V8: =IF(AND(16>=$D$8,16<=$D$8+$E$8-1),$F$8/$E$8,0) -> 2.1818182e+08 | W8: =IF(AND(17>=$D$8,17<=$D$8+$E$8-1),$F$8/$E$8,0) -> 2.1818182e+08 | X8: =IF(AND(18>=$D$8,18<=$D$8+$E$8-1),$F$8/$E$8,0) -> 2.1818182e+08 | Y8: =IF(AND(19>=$D$8,19<=$D$8+$E$8-1),$F$8/$E$8,0) -> 2.1818182e+08 | Z8: =IF(AND(20>=$D$8,20<=$D$8+$E$8-1),$F$8/$E$8,0) -> 2.1818182e+08 | AA8: =IF(AND(21>=$D$8,21<=$D$8+$E$8-1),$F$8/$E$8,0) -> 2.1818182e+08 | AB8: =IF(AND(22>=$D$8,22<=$D$8+$E$8-1),$F$8/$E$8,0) -> 2.1818182e+08 | AC8: =IF(AND(23>=$D$8,23<=$D$8+$E$8-1),$F$8/$E$8,0) -> 2.1818182e+08 | AD8: =IF(AND(24>=$D$8,24<=$D$8+$E$8-1),$F$8/$E$8,0) -> 2.1818182e+08 | AE8: =IF(AND(25>=$D$8,25<=$D$8+$E$8-1),$F$8/$E$8,0) -> 2.1818182e+08 | AF8: =IF(AND(26>=$D$8,26<=$D$8+$E$8-1),$F$8/$E$8,0) -> 2.1818182e+08 | AG8: =IF(AND(27>=$D$8,27<=$D$8+$E$8-1),$F$8/$E$8,0) -> 2.1818182e+08 | AH8: =IF(AND(28>=$D$8,28<=$D$8+$E$8-1),$F$8/$E$8,0) -> 2.1818182e+08 | AI8: =IF(AND(29>=$D$8,29<=$D$8+$E$8-1),$F$8/$E$8,0) -> 2.1818182e+08 | AJ8: =IF(AND(30>=$D$8,30<=$D$8+$E$8-1),$F$8/$E$8,0) -> 0 | AK8: =IF(AND(31>=$D$8,31<=$D$8+$E$8-1),$F$8/$E$8,0) -> 0 | AL8: =IF(AND(32>=$D$8,32<=$D$8+$E$8-1),$F$8/$E$8,0) -> 0 | AM8: =IF(AND(33>=$D$8,33<=$D$8+$E$8-1),$F$8/$E$8,0) -> 0 | AN8: =IF(AND(34>=$D$8,34<=$D$8+$E$8-1),$F$8/$E$8,0) -> 0 | AO8: =IF(AND(35>=$D$8,35<=$D$8+$E$8-1),$F$8/$E$8,0) -> 0 | AP8: =IF(AND(36>=$D$8,36<=$D$8+$E$8-1),$F$8/$E$8,0) -> 0 | AQ8: =IF(AND(37>=$D$8,37<=$D$8+$E$8-1),$F$8/$E$8,0) -> 0 | AR8: =IF(AND(38>=$D$8,38<=$D$8+$E$8-1),$F$8/$E$8,0) -> 0 | AS8: =IF(AND(39>=$D$8,39<=$D$8+$E$8-1),$F$8/$E$8,0) -> 0 | AT8: =IF(AND(40>=$D$8,40<=$D$8+$E$8-1),$F$8/$E$8,0) -> 0 | AU8: =IF(AND(41>=$D$8,41<=$D$8+$E$8-1),$F$8/$E$8,0) -> 0 | AV8: =IF(AND(42>=$D$8,42<=$D$8+$E$8-1),$F$8/$E$8,0) -> 0 | AW8: =IF(AND(43>=$D$8,43<=$D$8+$E$8-1),$F$8/$E$8,0) -> 0 | AX8: =IF(AND(44>=$D$8,44<=$D$8+$E$8-1),$F$8/$E$8,0) -> 0 | AY8: =IF(AND(45>=$D$8,45<=$D$8+$E$8-1),$F$8/$E$8,0) -> 0 | AZ8: =IF(AND(46>=$D$8,46<=$D$8+$E$8-1),$F$8/$E$8,0) -> 0 | BA8: =IF(AND(47>=$D$8,47<=$D$8+$E$8-1),$F$8/$E$8,0) -> 0 | BB8: =IF(AND(48>=$D$8,48<=$D$8+$E$8-1),$F$8/$E$8,0) -> 0 | BC8: =IF(AND(49>=$D$8,49<=$D$8+$E$8-1),$F$8/$E$8,0) -> 0 | BD8: =IF(AND(50>=$D$8,50<=$D$8+$E$8-1),$F$8/$E$8,0) -> 0 | BE8: =IF(AND(51>=$D$8,51<=$D$8+$E$8-1),$F$8/$E$8,0) -> 0 | BF8: =IF(AND(52>=$D$8,52<=$D$8+$E$8-1),$F$8/$E$8,0) -> 0 | BG8: =IF(AND(53>=$D$8,53<=$D$8+$E$8-1),$F$8/$E$8,0) -> 0 | BH8: =IF(AND(54>=$D$8,54<=$D$8+$E$8-1),$F$8/$E$8,0) -> 0 | BI8: =IF(AND(55>=$D$8,55<=$D$8+$E$8-1),$F$8/$E$8,0) -> 0 | BJ8: =IF(AND(56>=$D$8,56<=$D$8+$E$8-1),$F$8/$E$8,0) -> 0 | BK8: =IF(AND(57>=$D$8,57<=$D$8+$E$8-1),$F$8/$E$8,0) -> 0 | BL8: =IF(AND(58>=$D$8,58<=$D$8+$E$8-1),$F$8/$E$8,0) -> 0 | BM8: =IF(AND(59>=$D$8,59<=$D$8+$E$8-1),$F$8/$E$8,0) -> 0 | BN8: =IF(AND(60>=$D$8,60<=$D$8+$E$8-1),$F$8/$E$8,0) -> 0
A9: CH-06 | B9: Logements sociaux Phase 2 | C9: Bâtiment public | D9: 11 | E9: 18 | F9: 4500000000 | G9: =IF(AND(1>=$D$9,1<=$D$9+$E$9-1),$F$9/$E$9,0) -> 0 | H9: =IF(AND(2>=$D$9,2<=$D$9+$E$9-1),$F$9/$E$9,0) -> 0 | I9: =IF(AND(3>=$D$9,3<=$D$9+$E$9-1),$F$9/$E$9,0) -> 0 | J9: =IF(AND(4>=$D$9,4<=$D$9+$E$9-1),$F$9/$E$9,0) -> 0 | K9: =IF(AND(5>=$D$9,5<=$D$9+$E$9-1),$F$9/$E$9,0) -> 0 | L9: =IF(AND(6>=$D$9,6<=$D$9+$E$9-1),$F$9/$E$9,0) -> 0 | M9: =IF(AND(7>=$D$9,7<=$D$9+$E$9-1),$F$9/$E$9,0) -> 0 | N9: =IF(AND(8>=$D$9,8<=$D$9+$E$9-1),$F$9/$E$9,0) -> 0 | O9: =IF(AND(9>=$D$9,9<=$D$9+$E$9-1),$F$9/$E$9,0) -> 0 | P9: =IF(AND(10>=$D$9,10<=$D$9+$E$9-1),$F$9/$E$9,0) -> 0 | Q9: =IF(AND(11>=$D$9,11<=$D$9+$E$9-1),$F$9/$E$9,0) -> 250000000 | R9: =IF(AND(12>=$D$9,12<=$D$9+$E$9-1),$F$9/$E$9,0) -> 250000000 | S9: =IF(AND(13>=$D$9,13<=$D$9+$E$9-1),$F$9/$E$9,0) -> 250000000 | T9: =IF(AND(14>=$D$9,14<=$D$9+$E$9-1),$F$9/$E$9,0) -> 250000000 | U9: =IF(AND(15>=$D$9,15<=$D$9+$E$9-1),$F$9/$E$9,0) -> 250000000 | V9: =IF(AND(16>=$D$9,16<=$D$9+$E$9-1),$F$9/$E$9,0) -> 250000000 | W9: =IF(AND(17>=$D$9,17<=$D$9+$E$9-1),$F$9/$E$9,0) -> 250000000 | X9: =IF(AND(18>=$D$9,18<=$D$9+$E$9-1),$F$9/$E$9,0) -> 250000000 | Y9: =IF(AND(19>=$D$9,19<=$D$9+$E$9-1),$F$9/$E$9,0) -> 250000000 | Z9: =IF(AND(20>=$D$9,20<=$D$9+$E$9-1),$F$9/$E$9,0) -> 250000000 | AA9: =IF(AND(21>=$D$9,21<=$D$9+$E$9-1),$F$9/$E$9,0) -> 250000000 | AB9: =IF(AND(22>=$D$9,22<=$D$9+$E$9-1),$F$9/$E$9,0) -> 250000000 | AC9: =IF(AND(23>=$D$9,23<=$D$9+$E$9-1),$F$9/$E$9,0) -> 250000000 | AD9: =IF(AND(24>=$D$9,24<=$D$9+$E$9-1),$F$9/$E$9,0) -> 250000000 | AE9: =IF(AND(25>=$D$9,25<=$D$9+$E$9-1),$F$9/$E$9,0) -> 250000000 | AF9: =IF(AND(26>=$D$9,26<=$D$9+$E$9-1),$F$9/$E$9,0) -> 250000000 | AG9: =IF(AND(27>=$D$9,27<=$D$9+$E$9-1),$F$9/$E$9,0) -> 250000000 | AH9: =IF(AND(28>=$D$9,28<=$D$9+$E$9-1),$F$9/$E$9,0) -> 250000000 | AI9: =IF(AND(29>=$D$9,29<=$D$9+$E$9-1),$F$9/$E$9,0) -> 0 | AJ9: =IF(AND(30>=$D$9,30<=$D$9+$E$9-1),$F$9/$E$9,0) -> 0 | AK9: =IF(AND(31>=$D$9,31<=$D$9+$E$9-1),$F$9/$E$9,0) -> 0 | AL9: =IF(AND(32>=$D$9,32<=$D$9+$E$9-1),$F$9/$E$9,0) -> 0 | AM9: =IF(AND(33>=$D$9,33<=$D$9+$E$9-1),$F$9/$E$9,0) -> 0 | AN9: =IF(AND(34>=$D$9,34<=$D$9+$E$9-1),$F$9/$E$9,0) -> 0 | AO9: =IF(AND(35>=$D$9,35<=$D$9+$E$9-1),$F$9/$E$9,0) -> 0 | AP9: =IF(AND(36>=$D$9,36<=$D$9+$E$9-1),$F$9/$E$9,0) -> 0 | AQ9: =IF(AND(37>=$D$9,37<=$D$9+$E$9-1),$F$9/$E$9,0) -> 0 | AR9: =IF(AND(38>=$D$9,38<=$D$9+$E$9-1),$F$9/$E$9,0) -> 0 | AS9: =IF(AND(39>=$D$9,39<=$D$9+$E$9-1),$F$9/$E$9,0) -> 0 | AT9: =IF(AND(40>=$D$9,40<=$D$9+$E$9-1),$F$9/$E$9,0) -> 0 | AU9: =IF(AND(41>=$D$9,41<=$D$9+$E$9-1),$F$9/$E$9,0) -> 0 | AV9: =IF(AND(42>=$D$9,42<=$D$9+$E$9-1),$F$9/$E$9,0) -> 0 | AW9: =IF(AND(43>=$D$9,43<=$D$9+$E$9-1),$F$9/$E$9,0) -> 0 | AX9: =IF(AND(44>=$D$9,44<=$D$9+$E$9-1),$F$9/$E$9,0) -> 0 | AY9: =IF(AND(45>=$D$9,45<=$D$9+$E$9-1),$F$9/$E$9,0) -> 0 | AZ9: =IF(AND(46>=$D$9,46<=$D$9+$E$9-1),$F$9/$E$9,0) -> 0 | BA9: =IF(AND(47>=$D$9,47<=$D$9+$E$9-1),$F$9/$E$9,0) -> 0 | BB9: =IF(AND(48>=$D$9,48<=$D$9+$E$9-1),$F$9/$E$9,0) -> 0 | BC9: =IF(AND(49>=$D$9,49<=$D$9+$E$9-1),$F$9/$E$9,0) -> 0 | BD9: =IF(AND(50>=$D$9,50<=$D$9+$E$9-1),$F$9/$E$9,0) -> 0 | BE9: =IF(AND(51>=$D$9,51<=$D$9+$E$9-1),$F$9/$E$9,0) -> 0 | BF9: =IF(AND(52>=$D$9,52<=$D$9+$E$9-1),$F$9/$E$9,0) -> 0 | BG9: =IF(AND(53>=$D$9,53<=$D$9+$E$9-1),$F$9/$E$9,0) -> 0 | BH9: =IF(AND(54>=$D$9,54<=$D$9+$E$9-1),$F$9/$E$9,0) -> 0 | BI9: =IF(AND(55>=$D$9,55<=$D$9+$E$9-1),$F$9/$E$9,0) -> 0 | BJ9: =IF(AND(56>=$D$9,56<=$D$9+$E$9-1),$F$9/$E$9,0) -> 0 | BK9: =IF(AND(57>=$D$9,57<=$D$9+$E$9-1),$F$9/$E$9,0) -> 0 | BL9: =IF(AND(58>=$D$9,58<=$D$9+$E$9-1),$F$9/$E$9,0) -> 0 | BM9: =IF(AND(59>=$D$9,59<=$D$9+$E$9-1),$F$9/$E$9,0) -> 0 | BN9: =IF(AND(60>=$D$9,60<=$D$9+$E$9-1),$F$9/$E$9,0) -> 0
A10: CH-07 | B10: Ministère - extension | C10: Tertiaire public | D10: 14 | E10: 16 | F10: 3200000000 | G10: =IF(AND(1>=$D$10,1<=$D$10+$E$10-1),$F$10/$E$10,0) -> 0 | H10: =IF(AND(2>=$D$10,2<=$D$10+$E$10-1),$F$10/$E$10,0) -> 0 | I10: =IF(AND(3>=$D$10,3<=$D$10+$E$10-1),$F$10/$E$10,0) -> 0 | J10: =IF(AND(4>=$D$10,4<=$D$10+$E$10-1),$F$10/$E$10,0) -> 0 | K10: =IF(AND(5>=$D$10,5<=$D$10+$E$10-1),$F$10/$E$10,0) -> 0 | L10: =IF(AND(6>=$D$10,6<=$D$10+$E$10-1),$F$10/$E$10,0) -> 0 | M10: =IF(AND(7>=$D$10,7<=$D$10+$E$10-1),$F$10/$E$10,0) -> 0 | N10: =IF(AND(8>=$D$10,8<=$D$10+$E$10-1),$F$10/$E$10,0) -> 0 | O10: =IF(AND(9>=$D$10,9<=$D$10+$E$10-1),$F$10/$E$10,0) -> 0 | P10: =IF(AND(10>=$D$10,10<=$D$10+$E$10-1),$F$10/$E$10,0) -> 0 | Q10: =IF(AND(11>=$D$10,11<=$D$10+$E$10-1),$F$10/$E$10,0) -> 0 | R10: =IF(AND(12>=$D$10,12<=$D$10+$E$10-1),$F$10/$E$10,0) -> 0 | S10: =IF(AND(13>=$D$10,13<=$D$10+$E$10-1),$F$10/$E$10,0) -> 0 | T10: =IF(AND(14>=$D$10,14<=$D$10+$E$10-1),$F$10/$E$10,0) -> 200000000 | U10: =IF(AND(15>=$D$10,15<=$D$10+$E$10-1),$F$10/$E$10,0) -> 200000000 | V10: =IF(AND(16>=$D$10,16<=$D$10+$E$10-1),$F$10/$E$10,0) -> 200000000 | W10: =IF(AND(17>=$D$10,17<=$D$10+$E$10-1),$F$10/$E$10,0) -> 200000000 | X10: =IF(AND(18>=$D$10,18<=$D$10+$E$10-1),$F$10/$E$10,0) -> 200000000 | Y10: =IF(AND(19>=$D$10,19<=$D$10+$E$10-1),$F$10/$E$10,0) -> 200000000 | Z10: =IF(AND(20>=$D$10,20<=$D$10+$E$10-1),$F$10/$E$10,0) -> 200000000 | AA10: =IF(AND(21>=$D$10,21<=$D$10+$E$10-1),$F$10/$E$10,0) -> 200000000 | AB10: =IF(AND(22>=$D$10,22<=$D$10+$E$10-1),$F$10/$E$10,0) -> 200000000 | AC10: =IF(AND(23>=$D$10,23<=$D$10+$E$10-1),$F$10/$E$10,0) -> 200000000 | AD10: =IF(AND(24>=$D$10,24<=$D$10+$E$10-1),$F$10/$E$10,0) -> 200000000 | AE10: =IF(AND(25>=$D$10,25<=$D$10+$E$10-1),$F$10/$E$10,0) -> 200000000 | AF10: =IF(AND(26>=$D$10,26<=$D$10+$E$10-1),$F$10/$E$10,0) -> 200000000 | AG10: =IF(AND(27>=$D$10,27<=$D$10+$E$10-1),$F$10/$E$10,0) -> 200000000 | AH10: =IF(AND(28>=$D$10,28<=$D$10+$E$10-1),$F$10/$E$10,0) -> 200000000 | AI10: =IF(AND(29>=$D$10,29<=$D$10+$E$10-1),$F$10/$E$10,0) -> 200000000 | AJ10: =IF(AND(30>=$D$10,30<=$D$10+$E$10-1),$F$10/$E$10,0) -> 0 | AK10: =IF(AND(31>=$D$10,31<=$D$10+$E$10-1),$F$10/$E$10,0) -> 0 | AL10: =IF(AND(32>=$D$10,32<=$D$10+$E$10-1),$F$10/$E$10,0) -> 0 | AM10: =IF(AND(33>=$D$10,33<=$D$10+$E$10-1),$F$10/$E$10,0) -> 0 | AN10: =IF(AND(34>=$D$10,34<=$D$10+$E$10-1),$F$10/$E$10,0) -> 0 | AO10: =IF(AND(35>=$D$10,35<=$D$10+$E$10-1),$F$10/$E$10,0) -> 0 | AP10: =IF(AND(36>=$D$10,36<=$D$10+$E$10-1),$F$10/$E$10,0) -> 0 | AQ10: =IF(AND(37>=$D$10,37<=$D$10+$E$10-1),$F$10/$E$10,0) -> 0 | AR10: =IF(AND(38>=$D$10,38<=$D$10+$E$10-1),$F$10/$E$10,0) -> 0 | AS10: =IF(AND(39>=$D$10,39<=$D$10+$E$10-1),$F$10/$E$10,0) -> 0 | AT10: =IF(AND(40>=$D$10,40<=$D$10+$E$10-1),$F$10/$E$10,0) -> 0 | AU10: =IF(AND(41>=$D$10,41<=$D$10+$E$10-1),$F$10/$E$10,0) -> 0 | AV10: =IF(AND(42>=$D$10,42<=$D$10+$E$10-1),$F$10/$E$10,0) -> 0 | AW10: =IF(AND(43>=$D$10,43<=$D$10+$E$10-1),$F$10/$E$10,0) -> 0 | AX10: =IF(AND(44>=$D$10,44<=$D$10+$E$10-1),$F$10/$E$10,0) -> 0 | AY10: =IF(AND(45>=$D$10,45<=$D$10+$E$10-1),$F$10/$E$10,0) -> 0 | AZ10: =IF(AND(46>=$D$10,46<=$D$10+$E$10-1),$F$10/$E$10,0) -> 0 | BA10: =IF(AND(47>=$D$10,47<=$D$10+$E$10-1),$F$10/$E$10,0) -> 0 | BB10: =IF(AND(48>=$D$10,48<=$D$10+$E$10-1),$F$10/$E$10,0) -> 0 | BC10: =IF(AND(49>=$D$10,49<=$D$10+$E$10-1),$F$10/$E$10,0) -> 0 | BD10: =IF(AND(50>=$D$10,50<=$D$10+$E$10-1),$F$10/$E$10,0) -> 0 | BE10: =IF(AND(51>=$D$10,51<=$D$10+$E$10-1),$F$10/$E$10,0) -> 0 | BF10: =IF(AND(52>=$D$10,52<=$D$10+$E$10-1),$F$10/$E$10,0) -> 0 | BG10: =IF(AND(53>=$D$10,53<=$D$10+$E$10-1),$F$10/$E$10,0) -> 0 | BH10: =IF(AND(54>=$D$10,54<=$D$10+$E$10-1),$F$10/$E$10,0) -> 0 | BI10: =IF(AND(55>=$D$10,55<=$D$10+$E$10-1),$F$10/$E$10,0) -> 0 | BJ10: =IF(AND(56>=$D$10,56<=$D$10+$E$10-1),$F$10/$E$10,0) -> 0 | BK10: =IF(AND(57>=$D$10,57<=$D$10+$E$10-1),$F$10/$E$10,0) -> 0 | BL10: =IF(AND(58>=$D$10,58<=$D$10+$E$10-1),$F$10/$E$10,0) -> 0 | BM10: =IF(AND(59>=$D$10,59<=$D$10+$E$10-1),$F$10/$E$10,0) -> 0 | BN10: =IF(AND(60>=$D$10,60<=$D$10+$E$10-1),$F$10/$E$10,0) -> 0
A11: CH-08 | B11: Université - bloc pédagogique | C11: Public | D11: 18 | E11: 20 | F11: 5200000000 | G11: =IF(AND(1>=$D$11,1<=$D$11+$E$11-1),$F$11/$E$11,0) -> 0 | H11: =IF(AND(2>=$D$11,2<=$D$11+$E$11-1),$F$11/$E$11,0) -> 0 | I11: =IF(AND(3>=$D$11,3<=$D$11+$E$11-1),$F$11/$E$11,0) -> 0 | J11: =IF(AND(4>=$D$11,4<=$D$11+$E$11-1),$F$11/$E$11,0) -> 0 | K11: =IF(AND(5>=$D$11,5<=$D$11+$E$11-1),$F$11/$E$11,0) -> 0 | L11: =IF(AND(6>=$D$11,6<=$D$11+$E$11-1),$F$11/$E$11,0) -> 0 | M11: =IF(AND(7>=$D$11,7<=$D$11+$E$11-1),$F$11/$E$11,0) -> 0 | N11: =IF(AND(8>=$D$11,8<=$D$11+$E$11-1),$F$11/$E$11,0) -> 0 | O11: =IF(AND(9>=$D$11,9<=$D$11+$E$11-1),$F$11/$E$11,0) -> 0 | P11: =IF(AND(10>=$D$11,10<=$D$11+$E$11-1),$F$11/$E$11,0) -> 0 | Q11: =IF(AND(11>=$D$11,11<=$D$11+$E$11-1),$F$11/$E$11,0) -> 0 | R11: =IF(AND(12>=$D$11,12<=$D$11+$E$11-1),$F$11/$E$11,0) -> 0 | S11: =IF(AND(13>=$D$11,13<=$D$11+$E$11-1),$F$11/$E$11,0) -> 0 | T11: =IF(AND(14>=$D$11,14<=$D$11+$E$11-1),$F$11/$E$11,0) -> 0 | U11: =IF(AND(15>=$D$11,15<=$D$11+$E$11-1),$F$11/$E$11,0) -> 0 | V11: =IF(AND(16>=$D$11,16<=$D$11+$E$11-1),$F$11/$E$11,0) -> 0 | W11: =IF(AND(17>=$D$11,17<=$D$11+$E$11-1),$F$11/$E$11,0) -> 0 | X11: =IF(AND(18>=$D$11,18<=$D$11+$E$11-1),$F$11/$E$11,0) -> 260000000 | Y11: =IF(AND(19>=$D$11,19<=$D$11+$E$11-1),$F$11/$E$11,0) -> 260000000 | Z11: =IF(AND(20>=$D$11,20<=$D$11+$E$11-1),$F$11/$E$11,0) -> 260000000 | AA11: =IF(AND(21>=$D$11,21<=$D$11+$E$11-1),$F$11/$E$11,0) -> 260000000 | AB11: =IF(AND(22>=$D$11,22<=$D$11+$E$11-1),$F$11/$E$11,0) -> 260000000 | AC11: =IF(AND(23>=$D$11,23<=$D$11+$E$11-1),$F$11/$E$11,0) -> 260000000 | AD11: =IF(AND(24>=$D$11,24<=$D$11+$E$11-1),$F$11/$E$11,0) -> 260000000 | AE11: =IF(AND(25>=$D$11,25<=$D$11+$E$11-1),$F$11/$E$11,0) -> 260000000 | AF11: =IF(AND(26>=$D$11,26<=$D$11+$E$11-1),$F$11/$E$11,0) -> 260000000 | AG11: =IF(AND(27>=$D$11,27<=$D$11+$E$11-1),$F$11/$E$11,0) -> 260000000 | AH11: =IF(AND(28>=$D$11,28<=$D$11+$E$11-1),$F$11/$E$11,0) -> 260000000 | AI11: =IF(AND(29>=$D$11,29<=$D$11+$E$11-1),$F$11/$E$11,0) -> 260000000 | AJ11: =IF(AND(30>=$D$11,30<=$D$11+$E$11-1),$F$11/$E$11,0) -> 260000000 | AK11: =IF(AND(31>=$D$11,31<=$D$11+$E$11-1),$F$11/$E$11,0) -> 260000000 | AL11: =IF(AND(32>=$D$11,32<=$D$11+$E$11-1),$F$11/$E$11,0) -> 260000000 | AM11: =IF(AND(33>=$D$11,33<=$D$11+$E$11-1),$F$11/$E$11,0) -> 260000000 | AN11: =IF(AND(34>=$D$11,34<=$D$11+$E$11-1),$F$11/$E$11,0) -> 260000000 | AO11: =IF(AND(35>=$D$11,35<=$D$11+$E$11-1),$F$11/$E$11,0) -> 260000000 | AP11: =IF(AND(36>=$D$11,36<=$D$11+$E$11-1),$F$11/$E$11,0) -> 260000000 | AQ11: =IF(AND(37>=$D$11,37<=$D$11+$E$11-1),$F$11/$E$11,0) -> 260000000 | AR11: =IF(AND(38>=$D$11,38<=$D$11+$E$11-1),$F$11/$E$11,0) -> 0 | AS11: =IF(AND(39>=$D$11,39<=$D$11+$E$11-1),$F$11/$E$11,0) -> 0 | AT11: =IF(AND(40>=$D$11,40<=$D$11+$E$11-1),$F$11/$E$11,0) -> 0 | AU11: =IF(AND(41>=$D$11,41<=$D$11+$E$11-1),$F$11/$E$11,0) -> 0 | AV11: =IF(AND(42>=$D$11,42<=$D$11+$E$11-1),$F$11/$E$11,0) -> 0 | AW11: =IF(AND(43>=$D$11,43<=$D$11+$E$11-1),$F$11/$E$11,0) -> 0 | AX11: =IF(AND(44>=$D$11,44<=$D$11+$E$11-1),$F$11/$E$11,0) -> 0 | AY11: =IF(AND(45>=$D$11,45<=$D$11+$E$11-1),$F$11/$E$11,0) -> 0 | AZ11: =IF(AND(46>=$D$11,46<=$D$11+$E$11-1),$F$11/$E$11,0) -> 0 | BA11: =IF(AND(47>=$D$11,47<=$D$11+$E$11-1),$F$11/$E$11,0) -> 0 | BB11: =IF(AND(48>=$D$11,48<=$D$11+$E$11-1),$F$11/$E$11,0) -> 0 | BC11: =IF(AND(49>=$D$11,49<=$D$11+$E$11-1),$F$11/$E$11,0) -> 0 | BD11: =IF(AND(50>=$D$11,50<=$D$11+$E$11-1),$F$11/$E$11,0) -> 0 | BE11: =IF(AND(51>=$D$11,51<=$D$11+$E$11-1),$F$11/$E$11,0) -> 0 | BF11: =IF(AND(52>=$D$11,52<=$D$11+$E$11-1),$F$11/$E$11,0) -> 0 | BG11: =IF(AND(53>=$D$11,53<=$D$11+$E$11-1),$F$11/$E$11,0) -> 0 | BH11: =IF(AND(54>=$D$11,54<=$D$11+$E$11-1),$F$11/$E$11,0) -> 0 | BI11: =IF(AND(55>=$D$11,55<=$D$11+$E$11-1),$F$11/$E$11,0) -> 0 | BJ11: =IF(AND(56>=$D$11,56<=$D$11+$E$11-1),$F$11/$E$11,0) -> 0 | BK11: =IF(AND(57>=$D$11,57<=$D$11+$E$11-1),$F$11/$E$11,0) -> 0 | BL11: =IF(AND(58>=$D$11,58<=$D$11+$E$11-1),$F$11/$E$11,0) -> 0 | BM11: =IF(AND(59>=$D$11,59<=$D$11+$E$11-1),$F$11/$E$11,0) -> 0 | BN11: =IF(AND(60>=$D$11,60<=$D$11+$E$11-1),$F$11/$E$11,0) -> 0
A12: CH-09 | B12: Centre des congrès | C12: Tertiaire public | D12: 22 | E12: 24 | F12: 7800000000 | G12: =IF(AND(1>=$D$12,1<=$D$12+$E$12-1),$F$12/$E$12,0) -> 0 | H12: =IF(AND(2>=$D$12,2<=$D$12+$E$12-1),$F$12/$E$12,0) -> 0 | I12: =IF(AND(3>=$D$12,3<=$D$12+$E$12-1),$F$12/$E$12,0) -> 0 | J12: =IF(AND(4>=$D$12,4<=$D$12+$E$12-1),$F$12/$E$12,0) -> 0 | K12: =IF(AND(5>=$D$12,5<=$D$12+$E$12-1),$F$12/$E$12,0) -> 0 | L12: =IF(AND(6>=$D$12,6<=$D$12+$E$12-1),$F$12/$E$12,0) -> 0 | M12: =IF(AND(7>=$D$12,7<=$D$12+$E$12-1),$F$12/$E$12,0) -> 0 | N12: =IF(AND(8>=$D$12,8<=$D$12+$E$12-1),$F$12/$E$12,0) -> 0 | O12: =IF(AND(9>=$D$12,9<=$D$12+$E$12-1),$F$12/$E$12,0) -> 0 | P12: =IF(AND(10>=$D$12,10<=$D$12+$E$12-1),$F$12/$E$12,0) -> 0 | Q12: =IF(AND(11>=$D$12,11<=$D$12+$E$12-1),$F$12/$E$12,0) -> 0 | R12: =IF(AND(12>=$D$12,12<=$D$12+$E$12-1),$F$12/$E$12,0) -> 0 | S12: =IF(AND(13>=$D$12,13<=$D$12+$E$12-1),$F$12/$E$12,0) -> 0 | T12: =IF(AND(14>=$D$12,14<=$D$12+$E$12-1),$F$12/$E$12,0) -> 0 | U12: =IF(AND(15>=$D$12,15<=$D$12+$E$12-1),$F$12/$E$12,0) -> 0 | V12: =IF(AND(16>=$D$12,16<=$D$12+$E$12-1),$F$12/$E$12,0) -> 0 | W12: =IF(AND(17>=$D$12,17<=$D$12+$E$12-1),$F$12/$E$12,0) -> 0 | X12: =IF(AND(18>=$D$12,18<=$D$12+$E$12-1),$F$12/$E$12,0) -> 0 | Y12: =IF(AND(19>=$D$12,19<=$D$12+$E$12-1),$F$12/$E$12,0) -> 0 | Z12: =IF(AND(20>=$D$12,20<=$D$12+$E$12-1),$F$12/$E$12,0) -> 0 | AA12: =IF(AND(21>=$D$12,21<=$D$12+$E$12-1),$F$12/$E$12,0) -> 0 | AB12: =IF(AND(22>=$D$12,22<=$D$12+$E$12-1),$F$12/$E$12,0) -> 325000000 | AC12: =IF(AND(23>=$D$12,23<=$D$12+$E$12-1),$F$12/$E$12,0) -> 325000000 | AD12: =IF(AND(24>=$D$12,24<=$D$12+$E$12-1),$F$12/$E$12,0) -> 325000000 | AE12: =IF(AND(25>=$D$12,25<=$D$12+$E$12-1),$F$12/$E$12,0) -> 325000000 | AF12: =IF(AND(26>=$D$12,26<=$D$12+$E$12-1),$F$12/$E$12,0) -> 325000000 | AG12: =IF(AND(27>=$D$12,27<=$D$12+$E$12-1),$F$12/$E$12,0) -> 325000000 | AH12: =IF(AND(28>=$D$12,28<=$D$12+$E$12-1),$F$12/$E$12,0) -> 325000000 | AI12: =IF(AND(29>=$D$12,29<=$D$12+$E$12-1),$F$12/$E$12,0) -> 325000000 | AJ12: =IF(AND(30>=$D$12,30<=$D$12+$E$12-1),$F$12/$E$12,0) -> 325000000 | AK12: =IF(AND(31>=$D$12,31<=$D$12+$E$12-1),$F$12/$E$12,0) -> 325000000 | AL12: =IF(AND(32>=$D$12,32<=$D$12+$E$12-1),$F$12/$E$12,0) -> 325000000 | AM12: =IF(AND(33>=$D$12,33<=$D$12+$E$12-1),$F$12/$E$12,0) -> 325000000 | AN12: =IF(AND(34>=$D$12,34<=$D$12+$E$12-1),$F$12/$E$12,0) -> 325000000 | AO12: =IF(AND(35>=$D$12,35<=$D$12+$E$12-1),$F$12/$E$12,0) -> 325000000 | AP12: =IF(AND(36>=$D$12,36<=$D$12+$E$12-1),$F$12/$E$12,0) -> 325000000 | AQ12: =IF(AND(37>=$D$12,37<=$D$12+$E$12-1),$F$12/$E$12,0) -> 325000000 | AR12: =IF(AND(38>=$D$12,38<=$D$12+$E$12-1),$F$12/$E$12,0) -> 325000000 | AS12: =IF(AND(39>=$D$12,39<=$D$12+$E$12-1),$F$12/$E$12,0) -> 325000000 | AT12: =IF(AND(40>=$D$12,40<=$D$12+$E$12-1),$F$12/$E$12,0) -> 325000000 | AU12: =IF(AND(41>=$D$12,41<=$D$12+$E$12-1),$F$12/$E$12,0) -> 325000000 | AV12: =IF(AND(42>=$D$12,42<=$D$12+$E$12-1),$F$12/$E$12,0) -> 325000000 | AW12: =IF(AND(43>=$D$12,43<=$D$12+$E$12-1),$F$12/$E$12,0) -> 325000000 | AX12: =IF(AND(44>=$D$12,44<=$D$12+$E$12-1),$F$12/$E$12,0) -> 325000000 | AY12: =IF(AND(45>=$D$12,45<=$D$12+$E$12-1),$F$12/$E$12,0) -> 325000000 | AZ12: =IF(AND(46>=$D$12,46<=$D$12+$E$12-1),$F$12/$E$12,0) -> 0 | BA12: =IF(AND(47>=$D$12,47<=$D$12+$E$12-1),$F$12/$E$12,0) -> 0 | BB12: =IF(AND(48>=$D$12,48<=$D$12+$E$12-1),$F$12/$E$12,0) -> 0 | BC12: =IF(AND(49>=$D$12,49<=$D$12+$E$12-1),$F$12/$E$12,0) -> 0 | BD12: =IF(AND(50>=$D$12,50<=$D$12+$E$12-1),$F$12/$E$12,0) -> 0 | BE12: =IF(AND(51>=$D$12,51<=$D$12+$E$12-1),$F$12/$E$12,0) -> 0 | BF12: =IF(AND(52>=$D$12,52<=$D$12+$E$12-1),$F$12/$E$12,0) -> 0 | BG12: =IF(AND(53>=$D$12,53<=$D$12+$E$12-1),$F$12/$E$12,0) -> 0 | BH12: =IF(AND(54>=$D$12,54<=$D$12+$E$12-1),$F$12/$E$12,0) -> 0 | BI12: =IF(AND(55>=$D$12,55<=$D$12+$E$12-1),$F$12/$E$12,0) -> 0 | BJ12: =IF(AND(56>=$D$12,56<=$D$12+$E$12-1),$F$12/$E$12,0) -> 0 | BK12: =IF(AND(57>=$D$12,57<=$D$12+$E$12-1),$F$12/$E$12,0) -> 0 | BL12: =IF(AND(58>=$D$12,58<=$D$12+$E$12-1),$F$12/$E$12,0) -> 0 | BM12: =IF(AND(59>=$D$12,59<=$D$12+$E$12-1),$F$12/$E$12,0) -> 0 | BN12: =IF(AND(60>=$D$12,60<=$D$12+$E$12-1),$F$12/$E$12,0) -> 0
A13: CH-10 | B13: Logements résidentiels haut-standing | C13: Logement | D13: 28 | E13: 20 | F13: 5500000000 | G13: =IF(AND(1>=$D$13,1<=$D$13+$E$13-1),$F$13/$E$13,0) -> 0 | H13: =IF(AND(2>=$D$13,2<=$D$13+$E$13-1),$F$13/$E$13,0) -> 0 | I13: =IF(AND(3>=$D$13,3<=$D$13+$E$13-1),$F$13/$E$13,0) -> 0 | J13: =IF(AND(4>=$D$13,4<=$D$13+$E$13-1),$F$13/$E$13,0) -> 0 | K13: =IF(AND(5>=$D$13,5<=$D$13+$E$13-1),$F$13/$E$13,0) -> 0 | L13: =IF(AND(6>=$D$13,6<=$D$13+$E$13-1),$F$13/$E$13,0) -> 0 | M13: =IF(AND(7>=$D$13,7<=$D$13+$E$13-1),$F$13/$E$13,0) -> 0 | N13: =IF(AND(8>=$D$13,8<=$D$13+$E$13-1),$F$13/$E$13,0) -> 0 | O13: =IF(AND(9>=$D$13,9<=$D$13+$E$13-1),$F$13/$E$13,0) -> 0 | P13: =IF(AND(10>=$D$13,10<=$D$13+$E$13-1),$F$13/$E$13,0) -> 0 | Q13: =IF(AND(11>=$D$13,11<=$D$13+$E$13-1),$F$13/$E$13,0) -> 0 | R13: =IF(AND(12>=$D$13,12<=$D$13+$E$13-1),$F$13/$E$13,0) -> 0 | S13: =IF(AND(13>=$D$13,13<=$D$13+$E$13-1),$F$13/$E$13,0) -> 0 | T13: =IF(AND(14>=$D$13,14<=$D$13+$E$13-1),$F$13/$E$13,0) -> 0 | U13: =IF(AND(15>=$D$13,15<=$D$13+$E$13-1),$F$13/$E$13,0) -> 0 | V13: =IF(AND(16>=$D$13,16<=$D$13+$E$13-1),$F$13/$E$13,0) -> 0 | W13: =IF(AND(17>=$D$13,17<=$D$13+$E$13-1),$F$13/$E$13,0) -> 0 | X13: =IF(AND(18>=$D$13,18<=$D$13+$E$13-1),$F$13/$E$13,0) -> 0 | Y13: =IF(AND(19>=$D$13,19<=$D$13+$E$13-1),$F$13/$E$13,0) -> 0 | Z13: =IF(AND(20>=$D$13,20<=$D$13+$E$13-1),$F$13/$E$13,0) -> 0 | AA13: =IF(AND(21>=$D$13,21<=$D$13+$E$13-1),$F$13/$E$13,0) -> 0 | AB13: =IF(AND(22>=$D$13,22<=$D$13+$E$13-1),$F$13/$E$13,0) -> 0 | AC13: =IF(AND(23>=$D$13,23<=$D$13+$E$13-1),$F$13/$E$13,0) -> 0 | AD13: =IF(AND(24>=$D$13,24<=$D$13+$E$13-1),$F$13/$E$13,0) -> 0 | AE13: =IF(AND(25>=$D$13,25<=$D$13+$E$13-1),$F$13/$E$13,0) -> 0 | AF13: =IF(AND(26>=$D$13,26<=$D$13+$E$13-1),$F$13/$E$13,0) -> 0 | AG13: =IF(AND(27>=$D$13,27<=$D$13+$E$13-1),$F$13/$E$13,0) -> 0 | AH13: =IF(AND(28>=$D$13,28<=$D$13+$E$13-1),$F$13/$E$13,0) -> 275000000 | AI13: =IF(AND(29>=$D$13,29<=$D$13+$E$13-1),$F$13/$E$13,0) -> 275000000 | AJ13: =IF(AND(30>=$D$13,30<=$D$13+$E$13-1),$F$13/$E$13,0) -> 275000000 | AK13: =IF(AND(31>=$D$13,31<=$D$13+$E$13-1),$F$13/$E$13,0) -> 275000000 | AL13: =IF(AND(32>=$D$13,32<=$D$13+$E$13-1),$F$13/$E$13,0) -> 275000000 | AM13: =IF(AND(33>=$D$13,33<=$D$13+$E$13-1),$F$13/$E$13,0) -> 275000000 | AN13: =IF(AND(34>=$D$13,34<=$D$13+$E$13-1),$F$13/$E$13,0) -> 275000000 | AO13: =IF(AND(35>=$D$13,35<=$D$13+$E$13-1),$F$13/$E$13,0) -> 275000000 | AP13: =IF(AND(36>=$D$13,36<=$D$13+$E$13-1),$F$13/$E$13,0) -> 275000000 | AQ13: =IF(AND(37>=$D$13,37<=$D$13+$E$13-1),$F$13/$E$13,0) -> 275000000 | AR13: =IF(AND(38>=$D$13,38<=$D$13+$E$13-1),$F$13/$E$13,0) -> 275000000 | AS13: =IF(AND(39>=$D$13,39<=$D$13+$E$13-1),$F$13/$E$13,0) -> 275000000 | AT13: =IF(AND(40>=$D$13,40<=$D$13+$E$13-1),$F$13/$E$13,0) -> 275000000 | AU13: =IF(AND(41>=$D$13,41<=$D$13+$E$13-1),$F$13/$E$13,0) -> 275000000 | AV13: =IF(AND(42>=$D$13,42<=$D$13+$E$13-1),$F$13/$E$13,0) -> 275000000 | AW13: =IF(AND(43>=$D$13,43<=$D$13+$E$13-1),$F$13/$E$13,0) -> 275000000 | AX13: =IF(AND(44>=$D$13,44<=$D$13+$E$13-1),$F$13/$E$13,0) -> 275000000 | AY13: =IF(AND(45>=$D$13,45<=$D$13+$E$13-1),$F$13/$E$13,0) -> 275000000 | AZ13: =IF(AND(46>=$D$13,46<=$D$13+$E$13-1),$F$13/$E$13,0) -> 275000000 | BA13: =IF(AND(47>=$D$13,47<=$D$13+$E$13-1),$F$13/$E$13,0) -> 275000000 | BB13: =IF(AND(48>=$D$13,48<=$D$13+$E$13-1),$F$13/$E$13,0) -> 0 | BC13: =IF(AND(49>=$D$13,49<=$D$13+$E$13-1),$F$13/$E$13,0) -> 0 | BD13: =IF(AND(50>=$D$13,50<=$D$13+$E$13-1),$F$13/$E$13,0) -> 0 | BE13: =IF(AND(51>=$D$13,51<=$D$13+$E$13-1),$F$13/$E$13,0) -> 0 | BF13: =IF(AND(52>=$D$13,52<=$D$13+$E$13-1),$F$13/$E$13,0) -> 0 | BG13: =IF(AND(53>=$D$13,53<=$D$13+$E$13-1),$F$13/$E$13,0) -> 0 | BH13: =IF(AND(54>=$D$13,54<=$D$13+$E$13-1),$F$13/$E$13,0) -> 0 | BI13: =IF(AND(55>=$D$13,55<=$D$13+$E$13-1),$F$13/$E$13,0) -> 0 | BJ13: =IF(AND(56>=$D$13,56<=$D$13+$E$13-1),$F$13/$E$13,0) -> 0 | BK13: =IF(AND(57>=$D$13,57<=$D$13+$E$13-1),$F$13/$E$13,0) -> 0 | BL13: =IF(AND(58>=$D$13,58<=$D$13+$E$13-1),$F$13/$E$13,0) -> 0 | BM13: =IF(AND(59>=$D$13,59<=$D$13+$E$13-1),$F$13/$E$13,0) -> 0 | BN13: =IF(AND(60>=$D$13,60<=$D$13+$E$13-1),$F$13/$E$13,0) -> 0
A14: CH-11 | B14: Hôpital régional | C14: Santé publique | D14: 32 | E14: 26 | F14: 8500000000 | G14: =IF(AND(1>=$D$14,1<=$D$14+$E$14-1),$F$14/$E$14,0) -> 0 | H14: =IF(AND(2>=$D$14,2<=$D$14+$E$14-1),$F$14/$E$14,0) -> 0 | I14: =IF(AND(3>=$D$14,3<=$D$14+$E$14-1),$F$14/$E$14,0) -> 0 | J14: =IF(AND(4>=$D$14,4<=$D$14+$E$14-1),$F$14/$E$14,0) -> 0 | K14: =IF(AND(5>=$D$14,5<=$D$14+$E$14-1),$F$14/$E$14,0) -> 0 | L14: =IF(AND(6>=$D$14,6<=$D$14+$E$14-1),$F$14/$E$14,0) -> 0 | M14: =IF(AND(7>=$D$14,7<=$D$14+$E$14-1),$F$14/$E$14,0) -> 0 | N14: =IF(AND(8>=$D$14,8<=$D$14+$E$14-1),$F$14/$E$14,0) -> 0 | O14: =IF(AND(9>=$D$14,9<=$D$14+$E$14-1),$F$14/$E$14,0) -> 0 | P14: =IF(AND(10>=$D$14,10<=$D$14+$E$14-1),$F$14/$E$14,0) -> 0 | Q14: =IF(AND(11>=$D$14,11<=$D$14+$E$14-1),$F$14/$E$14,0) -> 0 | R14: =IF(AND(12>=$D$14,12<=$D$14+$E$14-1),$F$14/$E$14,0) -> 0 | S14: =IF(AND(13>=$D$14,13<=$D$14+$E$14-1),$F$14/$E$14,0) -> 0 | T14: =IF(AND(14>=$D$14,14<=$D$14+$E$14-1),$F$14/$E$14,0) -> 0 | U14: =IF(AND(15>=$D$14,15<=$D$14+$E$14-1),$F$14/$E$14,0) -> 0 | V14: =IF(AND(16>=$D$14,16<=$D$14+$E$14-1),$F$14/$E$14,0) -> 0 | W14: =IF(AND(17>=$D$14,17<=$D$14+$E$14-1),$F$14/$E$14,0) -> 0 | X14: =IF(AND(18>=$D$14,18<=$D$14+$E$14-1),$F$14/$E$14,0) -> 0 | Y14: =IF(AND(19>=$D$14,19<=$D$14+$E$14-1),$F$14/$E$14,0) -> 0 | Z14: =IF(AND(20>=$D$14,20<=$D$14+$E$14-1),$F$14/$E$14,0) -> 0 | AA14: =IF(AND(21>=$D$14,21<=$D$14+$E$14-1),$F$14/$E$14,0) -> 0 | AB14: =IF(AND(22>=$D$14,22<=$D$14+$E$14-1),$F$14/$E$14,0) -> 0 | AC14: =IF(AND(23>=$D$14,23<=$D$14+$E$14-1),$F$14/$E$14,0) -> 0 | AD14: =IF(AND(24>=$D$14,24<=$D$14+$E$14-1),$F$14/$E$14,0) -> 0 | AE14: =IF(AND(25>=$D$14,25<=$D$14+$E$14-1),$F$14/$E$14,0) -> 0 | AF14: =IF(AND(26>=$D$14,26<=$D$14+$E$14-1),$F$14/$E$14,0) -> 0 | AG14: =IF(AND(27>=$D$14,27<=$D$14+$E$14-1),$F$14/$E$14,0) -> 0 | AH14: =IF(AND(28>=$D$14,28<=$D$14+$E$14-1),$F$14/$E$14,0) -> 0 | AI14: =IF(AND(29>=$D$14,29<=$D$14+$E$14-1),$F$14/$E$14,0) -> 0 | AJ14: =IF(AND(30>=$D$14,30<=$D$14+$E$14-1),$F$14/$E$14,0) -> 0 | AK14: =IF(AND(31>=$D$14,31<=$D$14+$E$14-1),$F$14/$E$14,0) -> 0 | AL14: =IF(AND(32>=$D$14,32<=$D$14+$E$14-1),$F$14/$E$14,0) -> 3.2692308e+08 | AM14: =IF(AND(33>=$D$14,33<=$D$14+$E$14-1),$F$14/$E$14,0) -> 3.2692308e+08 | AN14: =IF(AND(34>=$D$14,34<=$D$14+$E$14-1),$F$14/$E$14,0) -> 3.2692308e+08 | AO14: =IF(AND(35>=$D$14,35<=$D$14+$E$14-1),$F$14/$E$14,0) -> 3.2692308e+08 | AP14: =IF(AND(36>=$D$14,36<=$D$14+$E$14-1),$F$14/$E$14,0) -> 3.2692308e+08 | AQ14: =IF(AND(37>=$D$14,37<=$D$14+$E$14-1),$F$14/$E$14,0) -> 3.2692308e+08 | AR14: =IF(AND(38>=$D$14,38<=$D$14+$E$14-1),$F$14/$E$14,0) -> 3.2692308e+08 | AS14: =IF(AND(39>=$D$14,39<=$D$14+$E$14-1),$F$14/$E$14,0) -> 3.2692308e+08 | AT14: =IF(AND(40>=$D$14,40<=$D$14+$E$14-1),$F$14/$E$14,0) -> 3.2692308e+08 | AU14: =IF(AND(41>=$D$14,41<=$D$14+$E$14-1),$F$14/$E$14,0) -> 3.2692308e+08 | AV14: =IF(AND(42>=$D$14,42<=$D$14+$E$14-1),$F$14/$E$14,0) -> 3.2692308e+08 | AW14: =IF(AND(43>=$D$14,43<=$D$14+$E$14-1),$F$14/$E$14,0) -> 3.2692308e+08 | AX14: =IF(AND(44>=$D$14,44<=$D$14+$E$14-1),$F$14/$E$14,0) -> 3.2692308e+08 | AY14: =IF(AND(45>=$D$14,45<=$D$14+$E$14-1),$F$14/$E$14,0) -> 3.2692308e+08 | AZ14: =IF(AND(46>=$D$14,46<=$D$14+$E$14-1),$F$14/$E$14,0) -> 3.2692308e+08 | BA14: =IF(AND(47>=$D$14,47<=$D$14+$E$14-1),$F$14/$E$14,0) -> 3.2692308e+08 | BB14: =IF(AND(48>=$D$14,48<=$D$14+$E$14-1),$F$14/$E$14,0) -> 3.2692308e+08 | BC14: =IF(AND(49>=$D$14,49<=$D$14+$E$14-1),$F$14/$E$14,0) -> 3.2692308e+08 | BD14: =IF(AND(50>=$D$14,50<=$D$14+$E$14-1),$F$14/$E$14,0) -> 3.2692308e+08 | BE14: =IF(AND(51>=$D$14,51<=$D$14+$E$14-1),$F$14/$E$14,0) -> 3.2692308e+08 | BF14: =IF(AND(52>=$D$14,52<=$D$14+$E$14-1),$F$14/$E$14,0) -> 3.2692308e+08 | BG14: =IF(AND(53>=$D$14,53<=$D$14+$E$14-1),$F$14/$E$14,0) -> 3.2692308e+08 | BH14: =IF(AND(54>=$D$14,54<=$D$14+$E$14-1),$F$14/$E$14,0) -> 3.2692308e+08 | BI14: =IF(AND(55>=$D$14,55<=$D$14+$E$14-1),$F$14/$E$14,0) -> 3.2692308e+08 | BJ14: =IF(AND(56>=$D$14,56<=$D$14+$E$14-1),$F$14/$E$14,0) -> 3.2692308e+08 | BK14: =IF(AND(57>=$D$14,57<=$D$14+$E$14-1),$F$14/$E$14,0) -> 3.2692308e+08 | BL14: =IF(AND(58>=$D$14,58<=$D$14+$E$14-1),$F$14/$E$14,0) -> 0 | BM14: =IF(AND(59>=$D$14,59<=$D$14+$E$14-1),$F$14/$E$14,0) -> 0 | BN14: =IF(AND(60>=$D$14,60<=$D$14+$E$14-1),$F$14/$E$14,0) -> 0
A15: CH-12 | B15: Complexe sportif olympique | C15: Public | D15: 40 | E15: 22 | F15: 6800000000 | G15: =IF(AND(1>=$D$15,1<=$D$15+$E$15-1),$F$15/$E$15,0) -> 0 | H15: =IF(AND(2>=$D$15,2<=$D$15+$E$15-1),$F$15/$E$15,0) -> 0 | I15: =IF(AND(3>=$D$15,3<=$D$15+$E$15-1),$F$15/$E$15,0) -> 0 | J15: =IF(AND(4>=$D$15,4<=$D$15+$E$15-1),$F$15/$E$15,0) -> 0 | K15: =IF(AND(5>=$D$15,5<=$D$15+$E$15-1),$F$15/$E$15,0) -> 0 | L15: =IF(AND(6>=$D$15,6<=$D$15+$E$15-1),$F$15/$E$15,0) -> 0 | M15: =IF(AND(7>=$D$15,7<=$D$15+$E$15-1),$F$15/$E$15,0) -> 0 | N15: =IF(AND(8>=$D$15,8<=$D$15+$E$15-1),$F$15/$E$15,0) -> 0 | O15: =IF(AND(9>=$D$15,9<=$D$15+$E$15-1),$F$15/$E$15,0) -> 0 | P15: =IF(AND(10>=$D$15,10<=$D$15+$E$15-1),$F$15/$E$15,0) -> 0 | Q15: =IF(AND(11>=$D$15,11<=$D$15+$E$15-1),$F$15/$E$15,0) -> 0 | R15: =IF(AND(12>=$D$15,12<=$D$15+$E$15-1),$F$15/$E$15,0) -> 0 | S15: =IF(AND(13>=$D$15,13<=$D$15+$E$15-1),$F$15/$E$15,0) -> 0 | T15: =IF(AND(14>=$D$15,14<=$D$15+$E$15-1),$F$15/$E$15,0) -> 0 | U15: =IF(AND(15>=$D$15,15<=$D$15+$E$15-1),$F$15/$E$15,0) -> 0 | V15: =IF(AND(16>=$D$15,16<=$D$15+$E$15-1),$F$15/$E$15,0) -> 0 | W15: =IF(AND(17>=$D$15,17<=$D$15+$E$15-1),$F$15/$E$15,0) -> 0 | X15: =IF(AND(18>=$D$15,18<=$D$15+$E$15-1),$F$15/$E$15,0) -> 0 | Y15: =IF(AND(19>=$D$15,19<=$D$15+$E$15-1),$F$15/$E$15,0) -> 0 | Z15: =IF(AND(20>=$D$15,20<=$D$15+$E$15-1),$F$15/$E$15,0) -> 0 | AA15: =IF(AND(21>=$D$15,21<=$D$15+$E$15-1),$F$15/$E$15,0) -> 0 | AB15: =IF(AND(22>=$D$15,22<=$D$15+$E$15-1),$F$15/$E$15,0) -> 0 | AC15: =IF(AND(23>=$D$15,23<=$D$15+$E$15-1),$F$15/$E$15,0) -> 0 | AD15: =IF(AND(24>=$D$15,24<=$D$15+$E$15-1),$F$15/$E$15,0) -> 0 | AE15: =IF(AND(25>=$D$15,25<=$D$15+$E$15-1),$F$15/$E$15,0) -> 0 | AF15: =IF(AND(26>=$D$15,26<=$D$15+$E$15-1),$F$15/$E$15,0) -> 0 | AG15: =IF(AND(27>=$D$15,27<=$D$15+$E$15-1),$F$15/$E$15,0) -> 0 | AH15: =IF(AND(28>=$D$15,28<=$D$15+$E$15-1),$F$15/$E$15,0) -> 0 | AI15: =IF(AND(29>=$D$15,29<=$D$15+$E$15-1),$F$15/$E$15,0) -> 0 | AJ15: =IF(AND(30>=$D$15,30<=$D$15+$E$15-1),$F$15/$E$15,0) -> 0 | AK15: =IF(AND(31>=$D$15,31<=$D$15+$E$15-1),$F$15/$E$15,0) -> 0 | AL15: =IF(AND(32>=$D$15,32<=$D$15+$E$15-1),$F$15/$E$15,0) -> 0 | AM15: =IF(AND(33>=$D$15,33<=$D$15+$E$15-1),$F$15/$E$15,0) -> 0 | AN15: =IF(AND(34>=$D$15,34<=$D$15+$E$15-1),$F$15/$E$15,0) -> 0 | AO15: =IF(AND(35>=$D$15,35<=$D$15+$E$15-1),$F$15/$E$15,0) -> 0 | AP15: =IF(AND(36>=$D$15,36<=$D$15+$E$15-1),$F$15/$E$15,0) -> 0 | AQ15: =IF(AND(37>=$D$15,37<=$D$15+$E$15-1),$F$15/$E$15,0) -> 0 | AR15: =IF(AND(38>=$D$15,38<=$D$15+$E$15-1),$F$15/$E$15,0) -> 0 | AS15: =IF(AND(39>=$D$15,39<=$D$15+$E$15-1),$F$15/$E$15,0) -> 0 | AT15: =IF(AND(40>=$D$15,40<=$D$15+$E$15-1),$F$15/$E$15,0) -> 3.0909091e+08 | AU15: =IF(AND(41>=$D$15,41<=$D$15+$E$15-1),$F$15/$E$15,0) -> 3.0909091e+08 | AV15: =IF(AND(42>=$D$15,42<=$D$15+$E$15-1),$F$15/$E$15,0) -> 3.0909091e+08 | AW15: =IF(AND(43>=$D$15,43<=$D$15+$E$15-1),$F$15/$E$15,0) -> 3.0909091e+08 | AX15: =IF(AND(44>=$D$15,44<=$D$15+$E$15-1),$F$15/$E$15,0) -> 3.0909091e+08 | AY15: =IF(AND(45>=$D$15,45<=$D$15+$E$15-1),$F$15/$E$15,0) -> 3.0909091e+08 | AZ15: =IF(AND(46>=$D$15,46<=$D$15+$E$15-1),$F$15/$E$15,0) -> 3.0909091e+08 | BA15: =IF(AND(47>=$D$15,47<=$D$15+$E$15-1),$F$15/$E$15,0) -> 3.0909091e+08 | BB15: =IF(AND(48>=$D$15,48<=$D$15+$E$15-1),$F$15/$E$15,0) -> 3.0909091e+08 | BC15: =IF(AND(49>=$D$15,49<=$D$15+$E$15-1),$F$15/$E$15,0) -> 3.0909091e+08 | BD15: =IF(AND(50>=$D$15,50<=$D$15+$E$15-1),$F$15/$E$15,0) -> 3.0909091e+08 | BE15: =IF(AND(51>=$D$15,51<=$D$15+$E$15-1),$F$15/$E$15,0) -> 3.0909091e+08 | BF15: =IF(AND(52>=$D$15,52<=$D$15+$E$15-1),$F$15/$E$15,0) -> 3.0909091e+08 | BG15: =IF(AND(53>=$D$15,53<=$D$15+$E$15-1),$F$15/$E$15,0) -> 3.0909091e+08 | BH15: =IF(AND(54>=$D$15,54<=$D$15+$E$15-1),$F$15/$E$15,0) -> 3.0909091e+08 | BI15: =IF(AND(55>=$D$15,55<=$D$15+$E$15-1),$F$15/$E$15,0) -> 3.0909091e+08 | BJ15: =IF(AND(56>=$D$15,56<=$D$15+$E$15-1),$F$15/$E$15,0) -> 3.0909091e+08 | BK15: =IF(AND(57>=$D$15,57<=$D$15+$E$15-1),$F$15/$E$15,0) -> 3.0909091e+08 | BL15: =IF(AND(58>=$D$15,58<=$D$15+$E$15-1),$F$15/$E$15,0) -> 3.0909091e+08 | BM15: =IF(AND(59>=$D$15,59<=$D$15+$E$15-1),$F$15/$E$15,0) -> 3.0909091e+08 | BN15: =IF(AND(60>=$D$15,60<=$D$15+$E$15-1),$F$15/$E$15,0) -> 3.0909091e+08
A16: TOTAL | B16: Tous chantiers — CA reconnu mensuel | G16: =SUM(G4:G15) -> 5.2878788e+08 | H16: =SUM(H4:H15) -> 5.2878788e+08 | I16: =SUM(I4:I15) -> 7.1878788e+08 | J16: =SUM(J4:J15) -> 7.1878788e+08 | K16: =SUM(K4:K15) -> 9.4795455e+08 | L16: =SUM(L4:L15) -> 9.4795455e+08 | M16: =SUM(M4:M15) -> 9.4795455e+08 | N16: =SUM(N4:N15) -> 1.1661364e+09 | ... BN16: =SUM(BN4:BN15) -> 3.0909091e+08
A18: AGRÉGATIONS ANNUELLES
A19: CA reconnu chantiers initiaux | B19: =SUM(G16:R16) -> 1.1669697e+10 | C19: =SUM(S16:AD16) -> 1.9617727e+10 | D19: =SUM(AE16:AP16) -> 1.5137191e+10 | E19: =SUM(AQ16:BB16) -> 1.2914895e+10 | F19: =SUM(BC16:BN16) -> 6.6513986e+09
A20: Avenants & révision prix | B20: =(B19)*'2. Hypothèses'!$C$18 -> 9.3357576e+08 | C20: =(C19)*'2. Hypothèses'!$D$18 -> 1.7655955e+09 | D20: =(D19)*'2. Hypothèses'!$E$18 -> 1.5137191e+09 | E20: =(E19)*'2. Hypothèses'!$F$18 -> 1.2914895e+09 | F20: =(F19)*'2. Hypothèses'!$G$18 -> 6.6513986e+08
A21: Réclamations recouvrées | B21: =B19*'2. Hypothèses'!$C$20 -> 1.7504545e+08 | C21: =C19*'2. Hypothèses'!$D$20 -> 3.9235455e+08 | D21: =D19*'2. Hypothèses'!$E$20 -> 3.0274382e+08 | E21: =E19*'2. Hypothèses'!$F$20 -> 2.582979e+08 | F21: =F19*'2. Hypothèses'!$G$20 -> 1.3302797e+08
A22: CA additionnel nouveaux chantiers (hors 12 typés) | B22: 0 | C22: =MAX(0,0.4*'3. Pipeline & Backlog'!C10+0.6*'3. Pipeline & Backlog'!B10-C19) -> 1.9442273e+10 | D22: =MAX(0,0.4*'3. Pipeline & Backlog'!D10+0.6*'3. Pipeline & Backlog'!C10-D19) -> 4.7102809e+10 | E22: =MAX(0,0.4*'3. Pipeline & Backlog'!E10+0.6*'3. Pipeline & Backlog'!D10-E19) -> 7.9165105e+10 | F22: =MAX(0,0.4*'3. Pipeline & Backlog'!F10+0.6*'3. Pipeline & Backlog'!E10-F19) -> 1.192686e+11
A23: CA TOTAL RECONNU (annuel) | B23: =B19+B20+B21+B22 -> 1.2778318e+10 | C23: =C19+C20+C21+C22 -> 41217950000 | D23: =D19+D20+D21+D22 -> 6.4056463e+10 | E23: =E19+E20+E21+E22 -> 9.3629787e+10 | F23: =F19+F20+F21+F22 -> 1.2671817e+11
A25: CA RECONNU MENSUEL Y1 (M01 → M12)
A26: Mois | B26: M01 | C26: M02 | D26: M03 | E26: M04 | F26: M05 | G26: M06 | H26: M07 | I26: M08 | J26: M09 | K26: M10 | L26: M11 | M26: M12
A27: CA chantiers initiaux | B27: =G16 -> 5.2878788e+08 | C27: =H16 -> 5.2878788e+08 | D27: =I16 -> 7.1878788e+08 | E27: =J16 -> 7.1878788e+08 | F27: =K16 -> 9.4795455e+08 | G27: =L16 -> 9.4795455e+08 | H27: =M16 -> 9.4795455e+08 | I27: =N16 -> 1.1661364e+09 | ... M27: =R16 -> 1.4161364e+09
A28: Avenants & révision | B28: =B27*'2. Hypothèses'!$C$18 -> 42303030 | C28: =C27*'2. Hypothèses'!$C$18 -> 42303030 | D28: =D27*'2. Hypothèses'!$C$18 -> 57503030 | E28: =E27*'2. Hypothèses'!$C$18 -> 57503030 | F28: =F27*'2. Hypothèses'!$C$18 -> 75836364 | G28: =G27*'2. Hypothèses'!$C$18 -> 75836364 | H28: =H27*'2. Hypothèses'!$C$18 -> 75836364 | I28: =I27*'2. Hypothèses'!$C$18 -> 93290909 | ... M28: =M27*'2. Hypothèses'!$C$18 -> 1.1329091e+08
A29: Réclamations | B29: =B27*'2. Hypothèses'!$C$20 -> 7931818.2 | C29: =C27*'2. Hypothèses'!$C$20 -> 7931818.2 | D29: =D27*'2. Hypothèses'!$C$20 -> 10781818 | E29: =E27*'2. Hypothèses'!$C$20 -> 10781818 | F29: =F27*'2. Hypothèses'!$C$20 -> 14219318 | G29: =G27*'2. Hypothèses'!$C$20 -> 14219318 | H29: =H27*'2. Hypothèses'!$C$20 -> 14219318 | I29: =I27*'2. Hypothèses'!$C$20 -> 17492045 | ... M29: =M27*'2. Hypothèses'!$C$20 -> 21242045
A30: CA TOTAL MENSUEL Y1 | B30: =B27+B28+B29 -> 5.7902273e+08 | C30: =C27+C28+C29 -> 5.7902273e+08 | D30: =D27+D28+D29 -> 7.8707273e+08 | E30: =E27+E28+E29 -> 7.8707273e+08 | F30: =F27+F28+F29 -> 1.0380102e+09 | G30: =G27+G28+G29 -> 1.0380102e+09 | H30: =H27+H28+H29 -> 1.0380102e+09 | I30: =I27+I28+I29 -> 1.2769193e+09 | ... M30: =M27+M28+M29 -> 1.5506693e+09

Sheet 5. Décomptes & encaissements
A1: DÉCOMPTES, AVANCES & ENCAISSEMENTS
A3: Poste | B3: M01 | C3: M02 | D3: M03 | E3: M04 | F3: M05 | G3: M06 | H3: M07 | I3: M08 | J3: M09 | K3: M10 | L3: M11 | M3: M12 | N3: Total Y1 | O3: Année 2 | P3: Année 3 | Q3: Année 4 | R3: Année 5
A4: CA RECONNU À L'AVANCEMENT (POC)
A5: CA reconnu (P&L) | B5: ='4. Portefeuille chantiers'!B30 -> 5.7902273e+08 | C5: ='4. Portefeuille chantiers'!C30 -> 5.7902273e+08 | D5: ='4. Portefeuille chantiers'!D30 -> 7.8707273e+08 | E5: ='4. Portefeuille chantiers'!E30 -> 7.8707273e+08 | F5: ='4. Portefeuille chantiers'!F30 -> 1.0380102e+09 | G5: ='4. Portefeuille chantiers'!G30 -> 1.0380102e+09 | H5: ='4. Portefeuille chantiers'!H30 -> 1.0380102e+09 | I5: ='4. Portefeuille chantiers'!I30 -> 1.2769193e+09 | ... M5: ='4. Portefeuille chantiers'!M30 -> 1.5506693e+09 | N5: =SUM(B5:M5) -> 1.2778318e+10 | O5: ='4. Portefeuille chantiers'!C23 -> 41217950000 | P5: ='4. Portefeuille chantiers'!D23 -> 6.4056463e+10 | Q5: ='4. Portefeuille chantiers'!E23 -> 9.3629787e+10 | R5: ='4. Portefeuille chantiers'!F23 -> 1.2671817e+11
A6: DÉCOMPTES FACTURÉS & STRUCTURE
A7: Décompte brut facturé HT | B7: =B5 -> 5.7902273e+08 | C7: =C5 -> 5.7902273e+08 | D7: =D5 -> 7.8707273e+08 | E7: =E5 -> 7.8707273e+08 | F7: =F5 -> 1.0380102e+09 | G7: =G5 -> 1.0380102e+09 | H7: =H5 -> 1.0380102e+09 | I7: =I5 -> 1.2769193e+09 | ... R7: =R5 -> 1.2671817e+11
A8: Avance de démarrage perçue | B8: =('3. Pipeline & Backlog'!B10*'2. Hypothèses'!$C$33)*0.5 -> 2362500000 | C8: =('3. Pipeline & Backlog'!B10*'2. Hypothèses'!$C$33)*0.3 -> 1417500000 | D8: =('3. Pipeline & Backlog'!B10*'2. Hypothèses'!$C$33)*0.2 -> 945000000 | E8: 0 | F8: 0 | G8: 0 | H8: 0 | I8: 0 | J8: 0 | K8: 0 | L8: 0 | M8: 0 | N8: =SUM(B8:M8) -> 4725000000 | O8: ='3. Pipeline & Backlog'!C10*'2. Hypothèses'!$D$33 -> 7560000000 | P8: ='3. Pipeline & Backlog'!D10*'2. Hypothèses'!$E$33 -> 12000000000 | Q8: ='3. Pipeline & Backlog'!E10*'2. Hypothèses'!$F$33 -> 16530000000 | R8: ='3. Pipeline & Backlog'!F10*'2. Hypothèses'!$G$33 -> 22425000000
A9: Remboursement avance (sur décompte) | B9: =-B7*'2. Hypothèses'!$C$33 -> -86853409 | C9: =-C7*'2. Hypothèses'!$C$33 -> -86853409 | D9: =-D7*'2. Hypothèses'!$C$33 -> -1.1806091e+08 | E9: =-E7*'2. Hypothèses'!$C$33 -> -1.1806091e+08 | F9: =-F7*'2. Hypothèses'!$C$33 -> -1.5570153e+08 | G9: =-G7*'2. Hypothèses'!$C$33 -> -1.5570153e+08 | H9: =-H7*'2. Hypothèses'!$C$33 -> -1.5570153e+08 | I9: =-I7*'2. Hypothèses'!$C$33 -> -1.915379e+08 | ... N9: =-N7*'2. Hypothèses'!$C$33 -> -1.9167477e+09 | O9: =-O7*'2. Hypothèses'!$D$33 -> -6182692500 | P9: =-P7*'2. Hypothèses'!$E$33 -> -9.6084694e+09 | Q9: =-Q7*'2. Hypothèses'!$F$33 -> -1.4044468e+10 | R9: =-R7*'2. Hypothèses'!$G$33 -> -1.9007725e+10
A10: Retenue garantie prélevée | B10: =-B7*'2. Hypothèses'!$C$34 -> -40531591 | C10: =-C7*'2. Hypothèses'!$C$34 -> -40531591 | D10: =-D7*'2. Hypothèses'!$C$34 -> -55095091 | E10: =-E7*'2. Hypothèses'!$C$34 -> -55095091 | F10: =-F7*'2. Hypothèses'!$C$34 -> -72660716 | G10: =-G7*'2. Hypothèses'!$C$34 -> -72660716 | H10: =-H7*'2. Hypothèses'!$C$34 -> -72660716 | I10: =-I7*'2. Hypothèses'!$C$34 -> -89384352 | ... N10: =-N7*'2. Hypothèses'!$C$34 -> -8.9448227e+08 | O10: =-O7*'2. Hypothèses'!$D$34 -> -2885256500 | P10: =-P7*'2. Hypothèses'!$E$34 -> -4.4839524e+09 | Q10: =-Q7*'2. Hypothèses'!$F$34 -> -6.5540851e+09 | R10: =-R7*'2. Hypothèses'!$G$34 -> -8.8702717e+09
A11: Décompte net dû par le maître d'ouvrage | B11: =B7+B8+B9+B10 -> 2.8141377e+09 | C11: =C7+C8+C9+C10 -> 1.8691377e+09 | D11: =D7+D8+D9+D10 -> 1.5589167e+09 | E11: =E7+E8+E9+E10 -> 6.1391673e+08 | F11: =F7+F8+F9+F10 -> 8.0964798e+08 | G11: =G7+G8+G9+G10 -> 8.0964798e+08 | H11: =H7+H8+H9+H10 -> 8.0964798e+08 | I11: =I7+I8+I9+I10 -> 9.9599707e+08 | ... R11: =R7+R8+R9+R10 -> 1.2126517e+11
A12: ENCAISSEMENTS RÉELS (TIMING)
A13: Encaissements décomptes (timing DSO) | B13: =IF(1-ROUNDUP('2. Hypothèses'!$C$36/30,0)<1,0,INDEX($B$11:$M$11,1,1-ROUNDUP('2. Hypothèses'!$C$36/30,0))) -> 0 | C13: =IF(2-ROUNDUP('2. Hypothèses'!$C$36/30,0)<1,0,INDEX($B$11:$M$11,1,2-ROUNDUP('2. Hypothèses'!$C$36/30,0))) -> 0 | D13: =IF(3-ROUNDUP('2. Hypothèses'!$C$36/30,0)<1,0,INDEX($B$11:$M$11,1,3-ROUNDUP('2. Hypothèses'!$C$36/30,0))) -> 0 | E13: =IF(4-ROUNDUP('2. Hypothèses'!$C$36/30,0)<1,0,INDEX($B$11:$M$11,1,4-ROUNDUP('2. Hypothèses'!$C$36/30,0))) -> 0 | F13: =IF(5-ROUNDUP('2. Hypothèses'!$C$36/30,0)<1,0,INDEX($B$11:$M$11,1,5-ROUNDUP('2. Hypothèses'!$C$36/30,0))) -> 2.8141377e+09 | G13: =IF(6-ROUNDUP('2. Hypothèses'!$C$36/30,0)<1,0,INDEX($B$11:$M$11,1,6-ROUNDUP('2. Hypothèses'!$C$36/30,0))) -> 1.8691377e+09 | H13: =IF(7-ROUNDUP('2. Hypothèses'!$C$36/30,0)<1,0,INDEX($B$11:$M$11,1,7-ROUNDUP('2. Hypothèses'!$C$36/30,0))) -> 1.5589167e+09 | I13: =IF(8-ROUNDUP('2. Hypothèses'!$C$36/30,0)<1,0,INDEX($B$11:$M$11,1,8-ROUNDUP('2. Hypothèses'!$C$36/30,0))) -> 6.1391673e+08 | J13: =IF(9-ROUNDUP('2. Hypothèses'!$C$36/30,0)<1,0,INDEX($B$11:$M$11,1,9-ROUNDUP('2. Hypothèses'!$C$36/30,0))) -> 8.0964798e+08 | K13: =IF(10-ROUNDUP('2. Hypothèses'!$C$36/30,0)<1,0,INDEX($B$11:$M$11,1,10-ROUNDUP('2. Hypothèses'!$C$36/30,0))) -> 8.0964798e+08 | L13: =IF(11-ROUNDUP('2. Hypothèses'!$C$36/30,0)<1,0,INDEX($B$11:$M$11,1,11-ROUNDUP('2. Hypothèses'!$C$36/30,0))) -> 8.0964798e+08 | M13: =IF(12-ROUNDUP('2. Hypothèses'!$C$36/30,0)<1,0,INDEX($B$11:$M$11,1,12-ROUNDUP('2. Hypothèses'!$C$36/30,0))) -> 9.9599707e+08 | N13: =SUM(B13:M13) -> 1.028105e+10 | O13: =O11+(N11-N13) -> 4.4121039e+10 | P13: =P11 -> 6.1964041e+10 | Q13: =Q11 -> 8.9561234e+10 | R13: =R11 -> 1.2126517e+11
A14: Libération retenue de garantie | B14: 0 | C14: 0 | D14: 0 | E14: 0 | F14: 0 | G14: 0 | H14: 0 | I14: 0 | J14: 0 | K14: 0 | L14: 0 | M14: 0 | N14: =SUM(B14:M14) -> 0 | O14: =-N10 -> 8.9448227e+08 | P14: =-O10 -> 2885256500 | Q14: =-P10 -> 4.4839524e+09 | R14: =-Q10 -> 6.5540851e+09
A15: TOTAL ENCAISSEMENTS CLIENT | B15: =B13+B14 -> 0 | C15: =C13+C14 -> 0 | D15: =D13+D14 -> 0 | E15: =E13+E14 -> 0 | F15: =F13+F14 -> 2.8141377e+09 | G15: =G13+G14 -> 1.8691377e+09 | H15: =H13+H14 -> 1.5589167e+09 | I15: =I13+I14 -> 6.1391673e+08 | ... R15: =R13+R14 -> 1.2781926e+11

Sheet 6. BFR & cautions
A1: BFR, RETENUES & CAUTIONS BANCAIRES
A3: Poste | B3: Année 1 | C3: Année 2 | D3: Année 3 | E3: Année 4 | F3: Année 5 | H3: Commentaire
A4: ENCOURS CAUTIONS BANCAIRES (fin de période)
A5: Encours caution soumission moyen | B5: ='2. Hypothèses'!$C$10*'2. Hypothèses'!$C$12*'2. Hypothèses'!$C$40*0.5 -> 735000000 | C5: ='2. Hypothèses'!$D$10*'2. Hypothèses'!$D$12*'2. Hypothèses'!$D$40*0.5 -> 1102500000 | D5: ='2. Hypothèses'!$E$10*'2. Hypothèses'!$E$12*'2. Hypothèses'!$E$40*0.5 -> 1575000000 | E5: ='2. Hypothèses'!$F$10*'2. Hypothèses'!$F$12*'2. Hypothèses'!$F$40*0.5 -> 2088000000 | F5: ='2. Hypothèses'!$G$10*'2. Hypothèses'!$G$12*'2. Hypothèses'!$G$40*0.5 -> 2681250000
A6: Encours caution restitution avance | B6: ='3. Pipeline & Backlog'!B13*'2. Hypothèses'!$C$41 -> 8.0582523e+09 | C6: ='3. Pipeline & Backlog'!C13*'2. Hypothèses'!$D$41 -> 9.4355598e+09 | D6: ='3. Pipeline & Backlog'!D13*'2. Hypothèses'!$E$41 -> 1.182709e+10 | E6: ='3. Pipeline & Backlog'!E13*'2. Hypothèses'!$F$41 -> 1.4312622e+10 | F6: ='3. Pipeline & Backlog'!F13*'2. Hypothèses'!$G$41 -> 1.7729897e+10
A7: Encours caution bonne fin | B7: ='3. Pipeline & Backlog'!B13*'2. Hypothèses'!$C$42 -> 2.6860841e+09 | C7: ='3. Pipeline & Backlog'!C13*'2. Hypothèses'!$D$42 -> 3.1451866e+09 | D7: ='3. Pipeline & Backlog'!D13*'2. Hypothèses'!$E$42 -> 3.9423634e+09 | E7: ='3. Pipeline & Backlog'!E13*'2. Hypothèses'!$F$42 -> 4.7708741e+09 | F7: ='3. Pipeline & Backlog'!F13*'2. Hypothèses'!$G$42 -> 5.9099657e+09
A8: Encours caution RG (remplacement RG cash) | B8: =-'5. Décomptes & encaissements'!N10*1.5 -> 1.3417234e+09 | C8: =-'5. Décomptes & encaissements'!O10*1.5 -> 4327884750 | D8: =-'5. Décomptes & encaissements'!P10*1.5 -> 6.7259286e+09 | E8: =-'5. Décomptes & encaissements'!Q10*1.5 -> 9.8311277e+09 | F8: =-'5. Décomptes & encaissements'!R10*1.5 -> 1.3305408e+10
A9: TOTAL ENCOURS CAUTIONS | B9: =B5+B6+B7+B8 -> 1.282106e+10 | C9: =C5+C6+C7+C8 -> 1.8011131e+10 | D9: =D5+D6+D7+D8 -> 2.4070382e+10 | E9: =E5+E6+E7+E8 -> 3.1002624e+10 | F9: =F5+F6+F7+F8 -> 3.962652e+10
A10: COÛT DES CAUTIONS (P&L)
A11: Commission cautions (an) | B11: =B9*'2. Hypothèses'!$C$44 -> 3.2052649e+08 | C11: =C9*'2. Hypothèses'!$D$44 -> 4.3226715e+08 | D11: =D9*'2. Hypothèses'!$E$44 -> 5.5361879e+08 | E11: =E9*'2. Hypothèses'!$F$44 -> 6.8205773e+08 | F11: =F9*'2. Hypothèses'!$G$44 -> 7.9253041e+08
A12: Contre-garantie cash bloquée (BFR) | B12: =B9*'2. Hypothèses'!$C$45 -> 2.564212e+09 | C12: =C9*'2. Hypothèses'!$D$45 -> 3.2420036e+09 | D12: =D9*'2. Hypothèses'!$E$45 -> 3.6105574e+09 | E12: =E9*'2. Hypothèses'!$F$45 -> 3.7203149e+09 | F12: =F9*'2. Hypothèses'!$G$45 -> 3.962652e+09
A13: BFR OPÉRATIONNEL
A14: Créances clients (CA × DSO/360) | B14: ='4. Portefeuille chantiers'!B23*'2. Hypothèses'!$C$36/360 -> 4.2594394e+09 | C14: ='4. Portefeuille chantiers'!C23*'2. Hypothèses'!$D$36/360 -> 1.2594374e+10 | D14: ='4. Portefeuille chantiers'!D23*'2. Hypothèses'!$E$36/360 -> 1.7793462e+10 | E14: ='4. Portefeuille chantiers'!E23*'2. Hypothèses'!$F$36/360 -> 2.4707861e+10 | F14: ='4. Portefeuille chantiers'!F23*'2. Hypothèses'!$G$36/360 -> 3.1679542e+10
A15: Retenue garantie cumulée non libérée | B15: =-'5. Décomptes & encaissements'!N10*1.5 -> 1.3417234e+09 | C15: =-'5. Décomptes & encaissements'!O10*1.5 -> 4327884750 | D15: =-'5. Décomptes & encaissements'!P10*1.5 -> 6.7259286e+09 | E15: =-'5. Décomptes & encaissements'!Q10*1.5 -> 9.8311277e+09 | F15: =-'5. Décomptes & encaissements'!R10*1.5 -> 1.3305408e+10
A16: Stocks chantier & en-cours | B16: ='4. Portefeuille chantiers'!B23*0.06 -> 7.6669909e+08 | C16: ='4. Portefeuille chantiers'!C23*0.06 -> 2473077000 | D16: ='4. Portefeuille chantiers'!D23*0.06 -> 3.8433878e+09 | E16: ='4. Portefeuille chantiers'!E23*0.06 -> 5.6177872e+09 | F16: ='4. Portefeuille chantiers'!F23*0.06 -> 7.6030901e+09
A17: Dettes fournisseurs (coûts × DPO/360) | B17: =-'4. Portefeuille chantiers'!B23*(1-'2. Hypothèses'!$C$17)*'2. Hypothèses'!$C$37/360 -> -1.8315589e+09 | C17: =-'4. Portefeuille chantiers'!C23*(1-'2. Hypothèses'!$D$17)*'2. Hypothèses'!$D$37/360 -> -6.3258104e+09 | D17: =-'4. Portefeuille chantiers'!D23*(1-'2. Hypothèses'!$E$17)*'2. Hypothèses'!$E$37/360 -> -9.7152302e+09 | E17: =-'4. Portefeuille chantiers'!E23*(1-'2. Hypothèses'!$F$17)*'2. Hypothèses'!$F$37/360 -> -1.5292865e+10 | F17: =-'4. Portefeuille chantiers'!F23*(1-'2. Hypothèses'!$G$17)*'2. Hypothèses'!$G$37/360 -> -2.0450904e+10
A18: Avances reçues non amorties | B18: =-'5. Décomptes & encaissements'!N8*0.3 -> -1417500000 | C18: =-'5. Décomptes & encaissements'!O8*0.3 -> -2268000000 | D18: =-'5. Décomptes & encaissements'!P8*0.3 -> -3600000000 | E18: =-'5. Décomptes & encaissements'!Q8*0.3 -> -4959000000 | F18: =-'5. Décomptes & encaissements'!R8*0.3 -> -6727500000
A19: BFR opérationnel net | B19: =B14+B15+B16+B17+B18 -> 3.118803e+09 | C19: =C14+C15+C16+C17+C18 -> 1.0801525e+10 | D19: =D14+D15+D16+D17+D18 -> 1.5047548e+10 | E19: =E14+E15+E16+E17+E18 -> 1.990491e+10 | F19: =F14+F15+F16+F17+F18 -> 2.5409635e+10
A20: BFR TOTAL (avec contre-garanties) | B20: =B19+B12 -> 5.6830149e+09 | C20: =C19+C12 -> 1.4043529e+10 | D20: =D19+D12 -> 1.8658105e+10 | E20: =E19+E12 -> 2.3625225e+10 | F20: =F19+F12 -> 2.9372287e+10
A21: Variation BFR (négatif = consomme cash) | B21: =-B20 -> -5.6830149e+09 | C21: =-(C20-B20) -> -8.3605137e+09 | D21: =-(D20-C20) -> -4.6145769e+09 | E21: =-(E20-D20) -> -4.9671196e+09 | F21: =-(F20-E20) -> -5.7470623e+09

Sheet 7. Sous-traitance & cotraitance
A1: SOUS-TRAITANCE & COTRAITANCE
A3: Poste | B3: Année 1 | C3: Année 2 | D3: Année 3 | E3: Année 4 | F3: Année 5 | H3: Commentaire
A4: SOUS-TRAITANCE
A5: CA total annuel | B5: ='4. Portefeuille chantiers'!B23 -> 1.2778318e+10 | C5: ='4. Portefeuille chantiers'!C23 -> 41217950000 | D5: ='4. Portefeuille chantiers'!D23 -> 6.4056463e+10 | E5: ='4. Portefeuille chantiers'!E23 -> 9.3629787e+10 | F5: ='4. Portefeuille chantiers'!F23 -> 1.2671817e+11
A6: Coûts directs totaux (1 - marge brute) | B6: =B5*(1-'2. Hypothèses'!$C$17) -> 1.0989354e+10 | C6: =C5*(1-'2. Hypothèses'!$D$17) -> 35035257500 | D6: =D5*(1-'2. Hypothèses'!$E$17) -> 5.3807429e+10 | E6: =E5*(1-'2. Hypothèses'!$F$17) -> 7.8649021e+10 | F6: =F5*(1-'2. Hypothèses'!$G$17) -> 1.0517608e+11
A7: Part sous-traitance dans coûts directs | B7: ='2. Hypothèses'!$C$24 -> 0.22 | C7: ='2. Hypothèses'!$D$24 -> 0.23 | D7: ='2. Hypothèses'!$E$24 -> 0.24 | E7: ='2. Hypothèses'!$F$24 -> 0.25 | F7: ='2. Hypothèses'!$G$24 -> 0.26
A8: Coût brut sous-traitance | B8: =B6*B7 -> 2417657800 | C8: =C6*C7 -> 8058109225 | D8: =D6*D7 -> 1.2913783e+10 | E8: =E6*E7 -> 1.9662255e+10 | F8: =F6*F7 -> 2.7345781e+10
A9: Mark-up (marge retenue sur ST) | B9: ='2. Hypothèses'!$C$28 -> 0.08 | C9: ='2. Hypothèses'!$D$28 -> 0.09 | D9: ='2. Hypothèses'!$E$28 -> 0.1 | E9: ='2. Hypothèses'!$F$28 -> 0.1 | F9: ='2. Hypothèses'!$G$28 -> 0.1
A10: Marge dégagée sur ST | B10: =B8*B9 -> 193412624 | C10: =C8*C9 -> 7.2522983e+08 | D10: =D8*D9 -> 1.2913783e+09 | E10: =E8*E9 -> 1.9662255e+09 | F10: =F8*F9 -> 2.7345781e+09
A11: Retenue garantie sur ST (cash conservé) | B11: =B8*'2. Hypothèses'!$C$31 -> 120882890 | C11: =C8*'2. Hypothèses'!$D$31 -> 4.0290546e+08 | D11: =D8*'2. Hypothèses'!$E$31 -> 6.4568915e+08 | E11: =E8*'2. Hypothèses'!$F$31 -> 9.8311277e+08 | F11: =F8*'2. Hypothèses'!$G$31 -> 1.367289e+09
A12: COTRAITANCE (GROUPEMENT)
A13: Part chantiers en cotraitance | B13: ='2. Hypothèses'!$C$29 -> 0.25 | C13: ='2. Hypothèses'!$D$29 -> 0.3 | D13: ='2. Hypothèses'!$E$29 -> 0.32 | E13: ='2. Hypothèses'!$F$29 -> 0.35 | F13: ='2. Hypothèses'!$G$29 -> 0.35
A14: CA réalisé en cotraitance (brut groupement) | B14: =B5*B13 -> 3.1945795e+09 | C14: =C5*C13 -> 12365385000 | D14: =D5*D13 -> 2.0498068e+10 | E14: =E5*E13 -> 3.2770426e+10 | F14: =F5*F13 -> 4.4351359e+10
A15: Quote-part propre dans groupements | B15: ='2. Hypothèses'!$C$30 -> 0.55 | C15: ='2. Hypothèses'!$D$30 -> 0.55 | D15: ='2. Hypothèses'!$E$30 -> 0.55 | E15: ='2. Hypothèses'!$F$30 -> 0.55 | F15: ='2. Hypothèses'!$G$30 -> 0.55
A16: CA effectivement comptabilisé en CT | B16: =B14*B15 -> 1757018750 | C16: =C14*C15 -> 6800961750 | D16: =D14*D15 -> 1.1273937e+10 | E16: =E14*E15 -> 1.8023734e+10 | F16: =F14*F15 -> 2.4393247e+10

Sheet 8. Parc matériel
A1: PARC MATÉRIEL & ENGINS — INVESTISSEMENTS & OPEX
A3: Poste | B3: Année 1 | C3: Année 2 | D3: Année 3 | E3: Année 4 | F3: Année 5 | H3: Commentaire
A4: ÉVOLUTION VALEUR BRUTE PARC
A5: Valeur brute début | B5: ='2. Hypothèses'!$C$47 -> 4500000000 | C5: =B7 -> 5300000000 | D5: =C7 -> 6500000000 | E5: =D7 -> 8000000000 | F5: =E7 -> 9500000000
A6: (+) Acquisitions de l'année | B6: ='2. Hypothèses'!$C$48 -> 800000000 | C6: ='2. Hypothèses'!$D$48 -> 1200000000 | D6: ='2. Hypothèses'!$E$48 -> 1500000000 | E6: ='2. Hypothèses'!$F$48 -> 1500000000 | F6: ='2. Hypothèses'!$G$48 -> 1800000000
A7: Valeur brute fin | B7: =B5+B6 -> 5300000000 | C7: =C5+C6 -> 6500000000 | D7: =D5+D6 -> 8000000000 | E7: =E5+E6 -> 9500000000 | F7: =F5+F6 -> 11300000000
A8: AMORTISSEMENTS
A9: Dotation amortissement engins annuelle | B9: =(B5+B7)/2/'2. Hypothèses'!$C$49 -> 700000000 | C9: =(C5+C7)/2/'2. Hypothèses'!$D$49 -> 8.4285714e+08 | D9: =(D5+D7)/2/'2. Hypothèses'!$E$49 -> 1.0357143e+09 | E9: =(E5+E7)/2/'2. Hypothèses'!$F$49 -> 1250000000 | F9: =(F5+F7)/2/'2. Hypothèses'!$G$49 -> 1.4857143e+09
A10: Cumul amortissements | B10: =B9 -> 700000000 | C10: =B10+C9 -> 1.5428571e+09 | D10: =C10+D9 -> 2.5785714e+09 | E10: =D10+E9 -> 3.8285714e+09 | F10: =E10+F9 -> 5.3142857e+09
A11: VNC fin de période (valeur nette comptable) | B11: =B7-B10 -> 4600000000 | C11: =C7-C10 -> 4.9571429e+09 | D11: =D7-D10 -> 5.4214286e+09 | E11: =E7-E10 -> 5.6714286e+09 | F11: =F7-F10 -> 5.9857143e+09
A12: OPEX ENGINS (P&L)
A13: Location engins externes (annuel) | B13: ='2. Hypothèses'!$C$50*12 -> 1140000000 | C13: ='2. Hypothèses'!$D$50*12 -> 1320000000 | D13: ='2. Hypothèses'!$E$50*12 -> 1500000000 | E13: ='2. Hypothèses'!$F$50*12 -> 1680000000 | F13: ='2. Hypothèses'!$G$50*12 -> 1860000000
A14: Carburant & maintenance engins propres | B14: ='2. Hypothèses'!$C$51 -> 550000000 | C14: ='2. Hypothèses'!$D$51 -> 720000000 | D14: ='2. Hypothèses'!$E$51 -> 880000000 | E14: ='2. Hypothèses'!$F$51 -> 1020000000 | F14: ='2. Hypothèses'!$G$51 -> 1150000000
A15: Taux d'utilisation engins | B15: ='2. Hypothèses'!$C$52 -> 0.65 | C15: ='2. Hypothèses'!$D$52 -> 0.7 | D15: ='2. Hypothèses'!$E$52 -> 0.72 | E15: ='2. Hypothèses'!$F$52 -> 0.75 | F15: ='2. Hypothèses'!$G$52 -> 0.75
A16: TOTAL OPEX MATÉRIEL | B16: =B13+B14 -> 1690000000 | C16: =C13+C14 -> 2040000000 | D16: =D13+D14 -> 2380000000 | E16: =E13+E14 -> 2700000000 | F16: =F13+F14 -> 3010000000

Sheet 9. Charges fixes & RH
A1: CHARGES FIXES & MASSE SALARIALE STRUCTURE
A3: Poste | B3: Année 1 | C3: Année 2 | D3: Année 3 | E3: Année 4 | F3: Année 5 | H3: Commentaire
A4: MASSE SALARIALE STRUCTURE (HORS PRODUCTION)
A5: Direction & Corporate | B5: ='2. Hypothèses'!$C$54*'2. Hypothèses'!$C$55*12 -> 316800000 | C5: ='2. Hypothèses'!$D$54*'2. Hypothèses'!$D$55*12 -> 386400000 | D5: ='2. Hypothèses'!$E$54*'2. Hypothèses'!$E$55*12 -> 460800000 | E5: ='2. Hypothèses'!$F$54*'2. Hypothèses'!$F$55*12 -> 540000000 | F5: ='2. Hypothèses'!$G$54*'2. Hypothèses'!$G$55*12 -> 624000000
A6: Bureau d'études & ingénierie | B6: ='2. Hypothèses'!$C$56*'2. Hypothèses'!$C$57*12 -> 313200000 | C6: ='2. Hypothèses'!$D$56*'2. Hypothèses'!$D$57*12 -> 396000000 | D6: ='2. Hypothèses'!$E$56*'2. Hypothèses'!$E$57*12 -> 483600000 | E6: ='2. Hypothèses'!$F$56*'2. Hypothèses'!$F$57*12 -> 576000000 | F6: ='2. Hypothèses'!$G$56*'2. Hypothèses'!$G$57*12 -> 633600000
A7: Encadrement chantiers | B7: ='2. Hypothèses'!$C$58*'2. Hypothèses'!$C$59*12 -> 480000000 | C7: ='2. Hypothèses'!$D$58*'2. Hypothèses'!$D$59*12 -> 624000000 | D7: ='2. Hypothèses'!$E$58*'2. Hypothèses'!$E$59*12 -> 777600000 | E7: ='2. Hypothèses'!$F$58*'2. Hypothèses'!$F$59*12 -> 940800000 | F7: ='2. Hypothèses'!$G$58*'2. Hypothèses'!$G$59*12 -> 1078800000
A8: Support (compta, achats, QHSE) | B8: ='2. Hypothèses'!$C$60*'2. Hypothèses'!$C$61*12 -> 250800000 | C8: ='2. Hypothèses'!$D$60*'2. Hypothèses'!$D$61*12 -> 312000000 | D8: ='2. Hypothèses'!$E$60*'2. Hypothèses'!$E$61*12 -> 378000000 | E8: ='2. Hypothèses'!$F$60*'2. Hypothèses'!$F$61*12 -> 448800000 | F8: ='2. Hypothèses'!$G$60*'2. Hypothèses'!$G$61*12 -> 524400000
A9: TOTAL MASSE SALARIALE | B9: =B5+B6+B7+B8 -> 1360800000 | C9: =C5+C6+C7+C8 -> 1718400000 | D9: =D5+D6+D7+D8 -> 2100000000 | E9: =E5+E6+E7+E8 -> 2505600000 | F9: =F5+F6+F7+F8 -> 2860800000
A10: AUTRES CHARGES FIXES STRUCTURE
A11: Loyer siège & dépôts | B11: ='2. Hypothèses'!$C$63*12 -> 264000000 | C11: ='2. Hypothèses'!$D$63*12 -> 288000000 | D11: ='2. Hypothèses'!$E$63*12 -> 312000000 | E11: ='2. Hypothèses'!$F$63*12 -> 336000000 | F11: ='2. Hypothèses'!$G$63*12 -> 360000000
A12: Assurances générales | B12: ='2. Hypothèses'!$C$64 -> 180000000 | C12: ='2. Hypothèses'!$D$64 -> 210000000 | D12: ='2. Hypothèses'!$E$64 -> 240000000 | E12: ='2. Hypothèses'!$F$64 -> 270000000 | F12: ='2. Hypothèses'!$G$64 -> 300000000
A13: IT, télécoms, ERP | B13: ='2. Hypothèses'!$C$65*12 -> 102000000 | C13: ='2. Hypothèses'!$D$65*12 -> 114000000 | D13: ='2. Hypothèses'!$E$65*12 -> 132000000 | E13: ='2. Hypothèses'!$F$65*12 -> 150000000 | F13: ='2. Hypothèses'!$G$65*12 -> 168000000
A14: Frais juridiques & honoraires | B14: ='2. Hypothèses'!$C$66 -> 95000000 | C14: ='2. Hypothèses'!$D$66 -> 110000000 | D14: ='2. Hypothèses'!$E$66 -> 125000000 | E14: ='2. Hypothèses'!$F$66 -> 140000000 | F14: ='2. Hypothèses'!$G$66 -> 155000000
A15: Marketing & relations institutionnelles | B15: ='2. Hypothèses'!$C$67 -> 120000000 | C15: ='2. Hypothèses'!$D$67 -> 145000000 | D15: ='2. Hypothèses'!$E$67 -> 170000000 | E15: ='2. Hypothèses'!$F$67 -> 195000000 | F15: ='2. Hypothèses'!$G$67 -> 220000000
A16: Formation & QHSE | B16: ='2. Hypothèses'!$C$68 -> 65000000 | C16: ='2. Hypothèses'!$D$68 -> 75000000 | D16: ='2. Hypothèses'!$E$68 -> 90000000 | E16: ='2. Hypothèses'!$F$68 -> 105000000 | F16: ='2. Hypothèses'!$G$68 -> 120000000
A17: Divers & déplacements | B17: ='2. Hypothèses'!$C$69*12 -> 144000000 | C17: ='2. Hypothèses'!$D$69*12 -> 168000000 | D17: ='2. Hypothèses'!$E$69*12 -> 192000000 | E17: ='2. Hypothèses'!$F$69*12 -> 216000000 | F17: ='2. Hypothèses'!$G$69*12 -> 240000000
A18: TOTAL AUTRES CHARGES FIXES | B18: =B11+B12+B13+B14+B15+B16+B17 -> 970000000 | C18: =C11+C12+C13+C14+C15+C16+C17 -> 1110000000 | D18: =D11+D12+D13+D14+D15+D16+D17 -> 1261000000 | E18: =E11+E12+E13+E14+E15+E16+E17 -> 1412000000 | F18: =F11+F12+F13+F14+F15+F16+F17 -> 1563000000
A19: COÛT COMMERCIAL
A20: Coût bureau d'études d'offres (AO) | B20: ='3. Pipeline & Backlog'!B17 -> 126000000 | C20: ='3. Pipeline & Backlog'!C17 -> 168000000 | D20: ='3. Pipeline & Backlog'!D17 -> 218400000 | E20: ='3. Pipeline & Backlog'!E17 -> 264000000 | F20: ='3. Pipeline & Backlog'!F17 -> 319000000
A21: TOTAL CHARGES FIXES STRUCTURE | B21: =B9+B18+B20 -> 2456800000 | C21: =C9+C18+C20 -> 2996400000 | D21: =D9+D18+D20 -> 3579400000 | E21: =E9+E18+E20 -> 4181600000 | F21: =F9+F18+F20 -> 4742800000

Sheet 10. CAPEX & Amort.
A1: CAPEX & AMORTISSEMENTS GLOBAL
A3: Poste | B3: Année 1 | C3: Année 2 | D3: Année 3 | E3: Année 4 | F3: Année 5 | H3: Commentaire
A4: INVESTISSEMENTS ANNUELS
A5: Engins & matériel (parc) | B5: ='2. Hypothèses'!$C$48 -> 800000000 | C5: ='2. Hypothèses'!$D$48 -> 1200000000 | D5: ='2. Hypothèses'!$E$48 -> 1500000000 | E5: ='2. Hypothèses'!$F$48 -> 1500000000 | F5: ='2. Hypothèses'!$G$48 -> 1800000000
A6: Aménagement siège & dépôts | B6: 120000000 | C6: 80000000 | D6: 100000000 | E6: 90000000 | F6: 110000000
A7: Systèmes IT, ERP, logiciels | B7: 150000000 | C7: 80000000 | D7: 90000000 | E7: 100000000 | F7: 110000000
A8: Véhicules de service | B8: 180000000 | C8: 150000000 | D8: 180000000 | E8: 200000000 | F8: 220000000
A9: TOTAL CAPEX ANNUEL | B9: =B5+B6+B7+B8 -> 1250000000 | C9: =C5+C6+C7+C8 -> 1510000000 | D9: =D5+D6+D7+D8 -> 1870000000 | E9: =E5+E6+E7+E8 -> 1890000000 | F9: =F5+F6+F7+F8 -> 2240000000
A10: DOTATIONS AUX AMORTISSEMENTS
A11: Amort. Engins & matériel (parc) | B11: =B5/7 -> 1.1428571e+08 | C11: =SUM(B5:C5)/7 -> 2.8571429e+08 | D11: =SUM(B5:D5)/7 -> 500000000 | E11: =SUM(B5:E5)/7 -> 7.1428571e+08 | F11: =SUM(B5:F5)/7 -> 9.7142857e+08
A12: Amort. Aménagement siège & dépôts | B12: =B6/5 -> 24000000 | C12: =SUM(B6:C6)/5 -> 40000000 | D12: =SUM(B6:D6)/5 -> 60000000 | E12: =SUM(B6:E6)/5 -> 78000000 | F12: =SUM(B6:F6)/5 -> 100000000
A13: Amort. Systèmes IT, ERP, logiciels | B13: =B7/4 -> 37500000 | C13: =SUM(B7:C7)/4 -> 57500000 | D13: =SUM(B7:D7)/4 -> 80000000 | E13: =SUM(B7:E7)/4 -> 105000000 | F13: =SUM(B7:F7)/4 -> 132500000
A14: Amort. Véhicules de service | B14: =B8/5 -> 36000000 | C14: =SUM(B8:C8)/5 -> 66000000 | D14: =SUM(B8:D8)/5 -> 102000000 | E14: =SUM(B8:E8)/5 -> 142000000 | F14: =SUM(B8:F8)/5 -> 186000000
A15: TOTAL AMORT. (hors parc matériel détaillé) | B15: =B12+B13+B14 -> 97500000 | C15: =C12+C13+C14 -> 163500000 | D15: =D12+D13+D14 -> 242000000 | E15: =E12+E13+E14 -> 325000000 | F15: =F12+F13+F14 -> 418500000
A16: Amort. parc matériel (engins) | B16: ='8. Parc matériel'!B9 -> 700000000 | C16: ='8. Parc matériel'!C9 -> 8.4285714e+08 | D16: ='8. Parc matériel'!D9 -> 1.0357143e+09 | E16: ='8. Parc matériel'!E9 -> 1250000000 | F16: ='8. Parc matériel'!F9 -> 1.4857143e+09
A17: TOTAL AMORTISSEMENTS | B17: =B15+B16 -> 797500000 | C17: =C15+C16 -> 1.0063571e+09 | D17: =D15+D16 -> 1.2777143e+09 | E17: =E15+E16 -> 1575000000 | F17: =F15+F16 -> 1.9042143e+09

Sheet 11. P&L
A1: COMPTE DE RÉSULTAT (P&L) — Vue annuelle 5 ans
A3: Poste | B3: Année 1 | C3: Année 2 | D3: Année 3 | E3: Année 4 | F3: Année 5 | H3: Commentaire
A4: CHIFFRE D'AFFAIRES
A5: CA reconnu à l'avancement | B5: ='4. Portefeuille chantiers'!B23 -> 1.2778318e+10 | C5: ='4. Portefeuille chantiers'!C23 -> 41217950000 | D5: ='4. Portefeuille chantiers'!D23 -> 6.4056463e+10 | E5: ='4. Portefeuille chantiers'!E23 -> 9.3629787e+10 | F5: ='4. Portefeuille chantiers'!F23 -> 1.2671817e+11
A6: COÛTS DIRECTS CHANTIER
A7: (-) Matériaux | B7: =-B5*(1-'2. Hypothèses'!$C$17)*'2. Hypothèses'!$C$22 -> -3.9561673e+09 | C7: =-C5*(1-'2. Hypothèses'!$D$17)*'2. Hypothèses'!$D$22 -> -12612692700 | D7: =-D5*(1-'2. Hypothèses'!$E$17)*'2. Hypothèses'!$E$22 -> -1.88326e+10 | E7: =-E5*(1-'2. Hypothèses'!$F$17)*'2. Hypothèses'!$F$22 -> -2.7527157e+10 | F7: =-F5*(1-'2. Hypothèses'!$G$17)*'2. Hypothèses'!$G$22 -> -3.6811628e+10
A8: (-) Main d'œuvre directe | B8: =-B5*(1-'2. Hypothèses'!$C$17)*'2. Hypothèses'!$C$23 -> -2417657800 | C8: =-C5*(1-'2. Hypothèses'!$D$17)*'2. Hypothèses'!$D$23 -> -7707756650 | D8: =-D5*(1-'2. Hypothèses'!$E$17)*'2. Hypothèses'!$E$23 -> -1.129956e+10 | E8: =-E5*(1-'2. Hypothèses'!$F$17)*'2. Hypothèses'!$F$23 -> -1.6516294e+10 | F8: =-F5*(1-'2. Hypothèses'!$G$17)*'2. Hypothèses'!$G$23 -> -2.1035216e+10
A9: (-) Sous-traitance | B9: =-'7. Sous-traitance & cotraitance'!B8 -> -2417657800 | C9: =-'7. Sous-traitance & cotraitance'!C8 -> -8058109225 | D9: =-'7. Sous-traitance & cotraitance'!D8 -> -1.2913783e+10 | E9: =-'7. Sous-traitance & cotraitance'!E8 -> -1.9662255e+10 | F9: =-'7. Sous-traitance & cotraitance'!F8 -> -2.7345781e+10
A10: (-) Matériel & engins (OPEX) | B10: =-'8. Parc matériel'!B16 -> -1690000000 | C10: =-'8. Parc matériel'!C16 -> -2040000000 | D10: =-'8. Parc matériel'!D16 -> -2380000000 | E10: =-'8. Parc matériel'!E16 -> -2700000000 | F10: =-'8. Parc matériel'!F16 -> -3010000000
A11: (-) Frais de chantier | B11: =-B5*(1-'2. Hypothèses'!$C$17)*'2. Hypothèses'!$C$26 -> -1.0989354e+09 | C11: =-C5*(1-'2. Hypothèses'!$D$17)*'2. Hypothèses'!$D$26 -> -3153173175 | D11: =-D5*(1-'2. Hypothèses'!$E$17)*'2. Hypothèses'!$E$26 -> -4.8426686e+09 | E11: =-E5*(1-'2. Hypothèses'!$F$17)*'2. Hypothèses'!$F$26 -> -6.2919217e+09 | F11: =-F5*(1-'2. Hypothèses'!$G$17)*'2. Hypothèses'!$G$26 -> -7.3623256e+09
A12: MARGE BRUTE CHANTIER | B12: =B5+B7+B8+B9+B10+B11 -> 1.1978999e+09 | C12: =C5+C7+C8+C9+C10+C11 -> 7646218250 | D12: =D5+D7+D8+D9+D10+D11 -> 1.3787851e+10 | E12: =E5+E7+E8+E9+E10+E11 -> 2.0932158e+10 | F12: =F5+F7+F8+F9+F10+F11 -> 3.1153218e+10
A13: Taux marge brute | B13: =IFERROR(B12/B5,0) -> 0.093744724 | C13: =IFERROR(C12/C5,0) -> 0.185507 | D13: =IFERROR(D12/D5,0) -> 0.21524528 | E13: =IFERROR(E12/E5,0) -> 0.22356302 | F13: =IFERROR(F12/F5,0) -> 0.2458465
A14: CHARGES STRUCTURE & AUTRES
A15: (-) Charges fixes structure (RH + autres) | B15: =-'9. Charges fixes & RH'!B21 -> -2456800000 | C15: =-'9. Charges fixes & RH'!C21 -> -2996400000 | D15: =-'9. Charges fixes & RH'!D21 -> -3579400000 | E15: =-'9. Charges fixes & RH'!E21 -> -4181600000 | F15: =-'9. Charges fixes & RH'!F21 -> -4742800000
A16: EBITDA | B16: =B12+B15 -> -1.2589001e+09 | C16: =C12+C15 -> 4649818250 | D16: =D12+D15 -> 1.0208451e+10 | E16: =E12+E15 -> 1.6750558e+10 | F16: =F12+F15 -> 2.6410418e+10
A17: Marge EBITDA | B17: =IFERROR(B16/B5,0) -> -0.098518449 | C17: =IFERROR(C16/C5,0) -> 0.11281052 | D17: =IFERROR(D16/D5,0) -> 0.15936645 | E17: =IFERROR(E16/E5,0) -> 0.17890202 | F17: =IFERROR(F16/F5,0) -> 0.20841856
A18: (-) Dotations aux amortissements | B18: =-'10. CAPEX & Amort.'!B17 -> -797500000 | C18: =-'10. CAPEX & Amort.'!C17 -> -1.0063571e+09 | D18: =-'10. CAPEX & Amort.'!D17 -> -1.2777143e+09 | E18: =-'10. CAPEX & Amort.'!E17 -> -1575000000 | F18: =-'10. CAPEX & Amort.'!F17 -> -1.9042143e+09
A19: RÉSULTAT D'EXPLOITATION (EBIT) | B19: =B16+B18 -> -2.0564001e+09 | C19: =C16+C18 -> 3.6434611e+09 | D19: =D16+D18 -> 8.930737e+09 | E19: =E16+E18 -> 1.5175558e+10 | F19: =F16+F18 -> 2.4506204e+10
A20: RÉSULTAT FINANCIER
A21: (-) Intérêts dette MLT | B21: =-'2. Hypothèses'!$C$72*'2. Hypothèses'!$C$73 -> -297500000 | C21: =-'2. Hypothèses'!$C$72*'2. Hypothèses'!$D$73 -> -297500000 | D21: =-'2. Hypothèses'!$C$72*'2. Hypothèses'!$E$73 -> -287000000 | E21: =-'2. Hypothèses'!$C$72*'2. Hypothèses'!$F$73 -> -280000000 | F21: =-'2. Hypothèses'!$C$72*'2. Hypothèses'!$G$73 -> -273000000
A22: (-) Intérêts découvert / CT (sur BFR) | B22: =-MAX(0,'6. BFR & cautions'!B19)*0.6*'2. Hypothèses'!$C$75 -> -2.151974e+08 | C22: =-MAX(0,'6. BFR & cautions'!C19)*0.6*'2. Hypothèses'!$D$75 -> -7.4530522e+08 | D22: =-MAX(0,'6. BFR & cautions'!D19)*0.6*'2. Hypothèses'!$E$75 -> -1.0111952e+09 | E22: =-MAX(0,'6. BFR & cautions'!E19)*0.6*'2. Hypothèses'!$F$75 -> -1.3137241e+09 | F22: =-MAX(0,'6. BFR & cautions'!F19)*0.6*'2. Hypothèses'!$G$75 -> -1.6465444e+09
A23: (-) Commissions cautions bancaires | B23: =-'6. BFR & cautions'!B11 -> -3.2052649e+08 | C23: =-'6. BFR & cautions'!C11 -> -4.3226715e+08 | D23: =-'6. BFR & cautions'!D11 -> -5.5361879e+08 | E23: =-'6. BFR & cautions'!E11 -> -6.8205773e+08 | F23: =-'6. BFR & cautions'!F11 -> -7.9253041e+08
A24: TOTAL FRAIS FINANCIERS | B24: =B21+B22+B23 -> -8.332239e+08 | C24: =C21+C22+C23 -> -1.4750724e+09 | D24: =D21+D22+D23 -> -1.851814e+09 | E24: =E21+E22+E23 -> -2.2757818e+09 | F24: =F21+F22+F23 -> -2.7120748e+09
A25: RÉSULTAT AVANT IMPÔT | B25: =B19+B24 -> -2.889624e+09 | C25: =C19+C24 -> 2.1683887e+09 | D25: =D19+D24 -> 7.0789229e+09 | E25: =E19+E24 -> 1.2899777e+10 | F25: =F19+F24 -> 2.1794129e+10
A26: (-) Impôt sur les sociétés | B26: =-MAX(0,B25)*'2. Hypothèses'!$C$6 -> 0 | C26: =-MAX(0,C25)*'2. Hypothèses'!$D$6 -> -6.5051662e+08 | D26: =-MAX(0,D25)*'2. Hypothèses'!$E$6 -> -2.1236769e+09 | E26: =-MAX(0,E25)*'2. Hypothèses'!$F$6 -> -3.869933e+09 | F26: =-MAX(0,F25)*'2. Hypothèses'!$G$6 -> -6.5382387e+09
A27: RÉSULTAT NET | B27: =B25+B26 -> -2.889624e+09 | C27: =C25+C26 -> 1.5178721e+09 | D27: =D25+D26 -> 4.9552461e+09 | E27: =E25+E26 -> 9.0298436e+09 | F27: =F25+F26 -> 1.525589e+10
A28: Marge nette | B28: =IFERROR(B27/B5,0) -> -0.22613492 | C28: =IFERROR(C27/C5,0) -> 0.036825512 | D28: =IFERROR(D27/D5,0) -> 0.077357472 | E28: =IFERROR(E27/E5,0) -> 0.096441996 | F28: =IFERROR(F27/F5,0) -> 0.12039229

Sheet 12. Trésorerie
A1: PLAN DE TRÉSORERIE ANNUEL — 5 ans
A3: Poste | B3: Année 1 | C3: Année 2 | D3: Année 3 | E3: Année 4 | F3: Année 5 | H3: Commentaire
A4: ENCAISSEMENTS
A5: Encaissements clients (décomptes + RG) | B5: ='5. Décomptes & encaissements'!N15 -> 1.028105e+10 | C5: ='5. Décomptes & encaissements'!O15 -> 4.5015522e+10 | D5: ='5. Décomptes & encaissements'!P15 -> 6.4849298e+10 | E5: ='5. Décomptes & encaissements'!Q15 -> 9.4045187e+10 | F5: ='5. Décomptes & encaissements'!R15 -> 1.2781926e+11
A6: DÉCAISSEMENTS OPÉRATIONNELS
A7: Coûts directs chantier | B7: ='11. P&L'!B7+'11. P&L'!B8+'11. P&L'!B9+'11. P&L'!B10+'11. P&L'!B11 -> -1.1580418e+10 | C7: ='11. P&L'!C7+'11. P&L'!C8+'11. P&L'!C9+'11. P&L'!C10+'11. P&L'!C11 -> -33571731750 | D7: ='11. P&L'!D7+'11. P&L'!D8+'11. P&L'!D9+'11. P&L'!D10+'11. P&L'!D11 -> -5.0268612e+10 | E7: ='11. P&L'!E7+'11. P&L'!E8+'11. P&L'!E9+'11. P&L'!E10+'11. P&L'!E11 -> -7.2697629e+10 | F7: ='11. P&L'!F7+'11. P&L'!F8+'11. P&L'!F9+'11. P&L'!F10+'11. P&L'!F11 -> -9.556495e+10
A8: Charges fixes structure | B8: ='11. P&L'!B15 -> -2456800000 | C8: ='11. P&L'!C15 -> -2996400000 | D8: ='11. P&L'!D15 -> -3579400000 | E8: ='11. P&L'!E15 -> -4181600000 | F8: ='11. P&L'!F15 -> -4742800000
A9: Variation BFR | B9: ='6. BFR & cautions'!B21 -> -5.6830149e+09 | C9: ='6. BFR & cautions'!C21 -> -8.3605137e+09 | D9: ='6. BFR & cautions'!D21 -> -4.6145769e+09 | E9: ='6. BFR & cautions'!E21 -> -4.9671196e+09 | F9: ='6. BFR & cautions'!F21 -> -5.7470623e+09
A10: CASH FLOW OPÉRATIONNEL (EBITDA - var BFR) | B10: ='11. P&L'!B16+B9 -> -6941915000 | C10: ='11. P&L'!C16+C9 -> -3.7106954e+09 | D10: ='11. P&L'!D16+D9 -> 5.5938744e+09 | E10: ='11. P&L'!E16+E9 -> 1.1783439e+10 | F10: ='11. P&L'!F16+F9 -> 2.0663356e+10
A11: FRAIS FINANCIERS, IS & INVESTISSEMENTS
A12: (-) Frais financiers & cautions | B12: ='11. P&L'!B24 -> -8.332239e+08 | C12: ='11. P&L'!C24 -> -1.4750724e+09 | D12: ='11. P&L'!D24 -> -1.851814e+09 | E12: ='11. P&L'!E24 -> -2.2757818e+09 | F12: ='11. P&L'!F24 -> -2.7120748e+09
A13: (-) Impôt sur les sociétés payé | B13: ='11. P&L'!B26 -> 0 | C13: ='11. P&L'!C26 -> -6.5051662e+08 | D13: ='11. P&L'!D26 -> -2.1236769e+09 | E13: ='11. P&L'!E26 -> -3.869933e+09 | F13: ='11. P&L'!F26 -> -6.5382387e+09
A14: (-) CAPEX (investissements) | B14: =-'10. CAPEX & Amort.'!B9 -> -1250000000 | C14: =-'10. CAPEX & Amort.'!C9 -> -1510000000 | D14: =-'10. CAPEX & Amort.'!D9 -> -1870000000 | E14: =-'10. CAPEX & Amort.'!E9 -> -1890000000 | F14: =-'10. CAPEX & Amort.'!F9 -> -2240000000
A15: CASH FLOW LIBRE (FCF) | B15: =B10+B12+B13+B14 -> -9.0251389e+09 | C15: =C10+C12+C13+C14 -> -7.3462844e+09 | D15: =D10+D12+D13+D14 -> -2.5161654e+08 | E15: =E10+E12+E13+E14 -> 3.7477239e+09 | F15: =F10+F12+F13+F14 -> 9.1730423e+09
A16: FINANCEMENT
A17: (+) Nouveaux emprunts MLT | B17: 0 | C17: 2000000000 | D17: 1500000000 | E17: 0 | F17: 1000000000
A18: (-) Remboursements emprunts | B18: -500000000 | C18: -600000000 | D18: -800000000 | E18: -900000000 | F18: -1000000000
A19: (+) Augmentation capital | B19: 0 | C19: 0 | D19: 3000000000 | E19: 0 | F19: 0
A20: (-) Dividendes versés | B20: 0 | C20: 0 | D20: -200000000 | E20: -400000000 | F20: -600000000
A21: CASH FLOW FINANCEMENT | B21: =B17+B18+B19+B20 -> -500000000 | C21: =C17+C18+C19+C20 -> 1400000000 | D21: =D17+D18+D19+D20 -> 3500000000 | E21: =E17+E18+E19+E20 -> -1300000000 | F21: =F17+F18+F19+F20 -> -600000000
A22: Variation de trésorerie nette | B22: =B15+B21 -> -9.5251389e+09 | C22: =C15+C21 -> -5.9462844e+09 | D22: =D15+D21 -> 3.2483835e+09 | E22: =E15+E21 -> 2.4477239e+09 | F22: =F15+F21 -> 8.5730423e+09
A23: SOLDE DE TRÉSORERIE
A24: Trésorerie début de période | B24: ='2. Hypothèses'!$C$76 -> 1800000000 | C24: =B25 -> -7.7251389e+09 | D24: =C25 -> -1.3671423e+10 | E24: =D25 -> -1.042304e+10 | F24: =E25 -> -7.9753159e+09
A25: TRÉSORERIE FIN DE PÉRIODE | B25: =B24+B22 -> -7.7251389e+09 | C25: =C24+C22 -> -1.3671423e+10 | D25: =D24+D22 -> -1.042304e+10 | E25: =E24+E22 -> -7.9753159e+09 | F25: =F24+F22 -> 5.9772639e+08

Sheet 13. KPIs Dashboard
A1: DASHBOARD KPIs — PILOTAGE STRATÉGIQUE
A3: Indicateur | B3: Unité | C3: Année 1 | D3: Année 2 | E3: Année 3 | F3: Année 4 | G3: Année 5 | H3: Commentaire
A4: ACTIVITÉ & PIPELINE
A5: Chiffre d'affaires | B5: FCFA | C5: ='11. P&L'!B5 -> 1.2778318e+10 | D5: ='11. P&L'!C5 -> 41217950000 | E5: ='11. P&L'!D5 -> 6.4056463e+10 | F5: ='11. P&L'!E5 -> 9.3629787e+10 | G5: ='11. P&L'!F5 -> 1.2671817e+11 | H5: CA total annuel
A6: Croissance CA YoY | B6: % | C6: ="N/A" -> N/A | D6: =IFERROR(C5/B5-1,0) -> 0 | E6: =IFERROR(D5/C5-1,0) -> 2.2256162 | F6: =IFERROR(E5/D5-1,0) -> 0.55409143 | G6: =IFERROR(F5/E5-1,0) -> 0.46167589 | H6: Taux de croissance annuel
A7: Backlog fin de période | B7: FCFA | C7: ='3. Pipeline & Backlog'!B13 -> 5.3721682e+10 | D7: ='3. Pipeline & Backlog'!C13 -> 6.2903732e+10 | E7: ='3. Pipeline & Backlog'!D13 -> 7.8847269e+10 | F7: ='3. Pipeline & Backlog'!E13 -> 9.5417481e+10 | G7: ='3. Pipeline & Backlog'!F13 -> 1.1819931e+11 | H7: Carnet de commandes clôture
A8: Book-to-bill | B8: ratio | C8: ='3. Pipeline & Backlog'!B15 -> 2.4651131 | D8: ='3. Pipeline & Backlog'!C15 -> 1.2227682 | E8: ='3. Pipeline & Backlog'!D15 -> 1.2488982 | F8: ='3. Pipeline & Backlog'!E15 -> 1.1769759 | G8: ='3. Pipeline & Backlog'!F15 -> 1.1797835 | H8: >1x signifie croissance future
A9: Couverture backlog | B9: mois | C9: ='3. Pipeline & Backlog'!B16 -> 50.449533 | D9: ='3. Pipeline & Backlog'!C16 -> 18.313496 | E9: ='3. Pipeline & Backlog'!D16 -> 14.770832 | F9: ='3. Pipeline & Backlog'!E16 -> 12.229119 | G9: ='3. Pipeline & Backlog'!F16 -> 11.193279 | H9: Backlog / (CA / 12)
A10: Hit-rate AO | B10: % | C10: ='3. Pipeline & Backlog'!B6 -> 0.32 | D10: ='3. Pipeline & Backlog'!C6 -> 0.35 | E10: ='3. Pipeline & Backlog'!D6 -> 0.38 | F10: ='3. Pipeline & Backlog'!E6 -> 0.4 | G10: ='3. Pipeline & Backlog'!F6 -> 0.42 | H10: Taux de transformation AO
A11: Nb chantiers gagnés | B11: nb | C11: ='3. Pipeline & Backlog'!B7 -> 9 | D11: ='3. Pipeline & Backlog'!C7 -> 12 | E11: ='3. Pipeline & Backlog'!D7 -> 16 | F11: ='3. Pipeline & Backlog'!E7 -> 19 | G11: ='3. Pipeline & Backlog'!F7 -> 23 | H11: Nouveaux contrats signés
A12: RENTABILITÉ
A13: Marge brute chantier | B13: FCFA | C13: ='11. P&L'!B12 -> 1.1978999e+09 | D13: ='11. P&L'!C12 -> 7646218250 | E13: ='11. P&L'!D12 -> 1.3787851e+10 | F13: ='11. P&L'!E12 -> 2.0932158e+10 | G13: ='11. P&L'!F12 -> 3.1153218e+10 | H13: Marge avant FG
A14: Taux marge brute | B14: % | C14: =IFERROR('11. P&L'!B12/'11. P&L'!B5,0) -> 0.093744724 | D14: =IFERROR('11. P&L'!C12/'11. P&L'!C5,0) -> 0.185507 | E14: =IFERROR('11. P&L'!D12/'11. P&L'!D5,0) -> 0.21524528 | F14: =IFERROR('11. P&L'!E12/'11. P&L'!E5,0) -> 0.22356302 | G14: =IFERROR('11. P&L'!F12/'11. P&L'!F5,0) -> 0.2458465 | H14: Marge brute / CA — cible 12-18%
A15: EBITDA | B15: FCFA | C15: ='11. P&L'!B16 -> -1.2589001e+09 | D15: ='11. P&L'!C16 -> 4649818250 | E15: ='11. P&L'!D16 -> 1.0208451e+10 | F15: ='11. P&L'!E16 -> 1.6750558e+10 | G15: ='11. P&L'!F16 -> 2.6410418e+10 | H15: Excédent brut d'exploitation
A16: Marge EBITDA | B16: % | C16: =IFERROR('11. P&L'!B16/'11. P&L'!B5,0) -> -0.098518449 | D16: =IFERROR('11. P&L'!C16/'11. P&L'!C5,0) -> 0.11281052 | E16: =IFERROR('11. P&L'!D16/'11. P&L'!D5,0) -> 0.15936645 | F16: =IFERROR('11. P&L'!E16/'11. P&L'!E5,0) -> 0.17890202 | G16: =IFERROR('11. P&L'!F16/'11. P&L'!F5,0) -> 0.20841856 | H16: Rentabilité opérationnelle
A17: Résultat net | B17: FCFA | C17: ='11. P&L'!B27 -> -2.889624e+09 | D17: ='11. P&L'!C27 -> 1.5178721e+09 | E17: ='11. P&L'!D27 -> 4.9552461e+09 | F17: ='11. P&L'!E27 -> 9.0298436e+09 | G17: ='11. P&L'!F27 -> 1.525589e+10 | H17: Bottom line
A18: Marge nette | B18: % | C18: =IFERROR('11. P&L'!B27/'11. P&L'!B5,0) -> -0.22613492 | D18: =IFERROR('11. P&L'!C27/'11. P&L'!C5,0) -> 0.036825512 | E18: =IFERROR('11. P&L'!D27/'11. P&L'!D5,0) -> 0.077357472 | F18: =IFERROR('11. P&L'!E27/'11. P&L'!E5,0) -> 0.096441996 | G18: =IFERROR('11. P&L'!F27/'11. P&L'!F5,0) -> 0.12039229 | H18: Cible 4-8% en BTP
A19: BFR & CASH MANAGEMENT
A20: BFR opérationnel | B20: FCFA | C20: ='6. BFR & cautions'!B19 -> 3.118803e+09 | D20: ='6. BFR & cautions'!C19 -> 1.0801525e+10 | E20: ='6. BFR & cautions'!D19 -> 1.5047548e+10 | F20: ='6. BFR & cautions'!E19 -> 1.990491e+10 | G20: ='6. BFR & cautions'!F19 -> 2.5409635e+10 | H20: Hors contre-garanties
A21: BFR / CA (jours) | B21: jours | C21: =IFERROR('6. BFR & cautions'!B19/'11. P&L'!B5*360,0) -> 87.865167 | D21: =IFERROR('6. BFR & cautions'!C19/'11. P&L'!C5*360,0) -> 94.341155 | E21: =IFERROR('6. BFR & cautions'!D19/'11. P&L'!D5*360,0) -> 84.567849 | F21: =IFERROR('6. BFR & cautions'!E19/'11. P&L'!E5*360,0) -> 76.532991 | G21: =IFERROR('6. BFR & cautions'!F19/'11. P&L'!F5*360,0) -> 72.187508 | H21: BFR en jours de CA
A22: DSO réel | B22: jours | C22: =IFERROR('6. BFR & cautions'!B14/'11. P&L'!B5*360,0) -> 120 | D22: =IFERROR('6. BFR & cautions'!C14/'11. P&L'!C5*360,0) -> 110 | E22: =IFERROR('6. BFR & cautions'!D14/'11. P&L'!D5*360,0) -> 100 | F22: =IFERROR('6. BFR & cautions'!E14/'11. P&L'!E5*360,0) -> 95 | G22: =IFERROR('6. BFR & cautions'!F14/'11. P&L'!F5*360,0) -> 90 | H22: Délai recouvrement clients
A23: Total encours cautions | B23: FCFA | C23: ='6. BFR & cautions'!B9 -> 1.282106e+10 | D23: ='6. BFR & cautions'!C9 -> 1.8011131e+10 | E23: ='6. BFR & cautions'!D9 -> 2.4070382e+10 | F23: ='6. BFR & cautions'!E9 -> 3.1002624e+10 | G23: ='6. BFR & cautions'!F9 -> 3.962652e+10 | H23: Engagements hors bilan
A24: Coût cautions / CA | B24: % | C24: =IFERROR('6. BFR & cautions'!B11/'11. P&L'!B5,0) -> 0.025083621 | D24: =IFERROR('6. BFR & cautions'!C11/'11. P&L'!C5,0) -> 0.010487352 | E24: =IFERROR('6. BFR & cautions'!D11/'11. P&L'!D5,0) -> 0.0086426688 | F24: =IFERROR('6. BFR & cautions'!E11/'11. P&L'!E5,0) -> 0.0072846233 | G24: =IFERROR('6. BFR & cautions'!F11/'11. P&L'!F5,0) -> 0.0062542761 | H24: Poids commissions cautions
A25: Cash flow libre (FCF) | B25: FCFA | C25: ='12. Trésorerie'!B15 -> -9.0251389e+09 | D25: ='12. Trésorerie'!C15 -> -7.3462844e+09 | E25: ='12. Trésorerie'!D15 -> -2.5161654e+08 | F25: ='12. Trésorerie'!E15 -> 3.7477239e+09 | G25: ='12. Trésorerie'!F15 -> 9.1730423e+09 | H25: FCF disponible
A26: Trésorerie fin de période | B26: FCFA | C26: ='12. Trésorerie'!B25 -> -7.7251389e+09 | D26: ='12. Trésorerie'!C25 -> -1.3671423e+10 | E26: ='12. Trésorerie'!D25 -> -1.042304e+10 | F26: ='12. Trésorerie'!E25 -> -7.9753159e+09 | G26: ='12. Trésorerie'!F25 -> 5.9772639e+08 | H26: Cash en banque
A27: STRUCTURE FINANCIÈRE
A28: Charges fixes / CA | B28: % | C28: =IFERROR(-'11. P&L'!B15/'11. P&L'!B5,0) -> 0.19226317 | D28: =IFERROR(-'11. P&L'!C15/'11. P&L'!C5,0) -> 0.072696483 | E28: =IFERROR(-'11. P&L'!D15/'11. P&L'!D5,0) -> 0.055878827 | F28: =IFERROR(-'11. P&L'!E15/'11. P&L'!E5,0) -> 0.044661001 | G28: =IFERROR(-'11. P&L'!F15/'11. P&L'!F5,0) -> 0.03742794 | H28: Poids structure
A29: Frais financiers / CA | B29: % | C29: =IFERROR(-'11. P&L'!B24/'11. P&L'!B5,0) -> 0.065206069 | D29: =IFERROR(-'11. P&L'!C24/'11. P&L'!C5,0) -> 0.035787136 | E29: =IFERROR(-'11. P&L'!D24/'11. P&L'!D5,0) -> 0.02890909 | F29: =IFERROR(-'11. P&L'!E24/'11. P&L'!E5,0) -> 0.024306173 | G29: =IFERROR(-'11. P&L'!F24/'11. P&L'!F5,0) -> 0.021402415 | H29: Poids du financement
A30: Couverture intérêts (EBITDA / FF) | B30: x | C30: =IFERROR('11. P&L'!B16/(-'11. P&L'!B24),0) -> -1.5108785 | D30: =IFERROR('11. P&L'!C16/(-'11. P&L'!C24),0) -> 3.1522645 | E30: =IFERROR('11. P&L'!D16/(-'11. P&L'!D24),0) -> 5.5126763 | F30: =IFERROR('11. P&L'!E16/(-'11. P&L'!E24),0) -> 7.3603534 | G30: =IFERROR('11. P&L'!F16/(-'11. P&L'!F24),0) -> 9.7380862 | H30: Capacité à servir la dette
A31: PRODUCTIVITÉ & RH
A32: ETP structure (total) | B32: nb | C32: ='2. Hypothèses'!$C$54+'2. Hypothèses'!$C$56+'2. Hypothèses'!$C$58+'2. Hypothèses'!$C$60 -> 84 | D32: ='2. Hypothèses'!$D$54+'2. Hypothèses'!$D$56+'2. Hypothèses'!$D$58+'2. Hypothèses'!$D$60 -> 102 | E32: ='2. Hypothèses'!$E$54+'2. Hypothèses'!$E$56+'2. Hypothèses'!$E$58+'2. Hypothèses'!$E$60 -> 120 | F32: ='2. Hypothèses'!$F$54+'2. Hypothèses'!$F$56+'2. Hypothèses'!$F$58+'2. Hypothèses'!$F$60 -> 138 | G32: ='2. Hypothèses'!$G$54+'2. Hypothèses'!$G$56+'2. Hypothèses'!$G$58+'2. Hypothèses'!$G$60 -> 152 | H32: Effectif total hors production directe
A33: CA / ETP | B33: FCFA | C33: =IFERROR('11. P&L'!B5/C32,0) -> 1.5212284e+08 | D33: =IFERROR('11. P&L'!C5/D32,0) -> 4.0409755e+08 | E33: =IFERROR('11. P&L'!D5/E32,0) -> 5.3380386e+08 | F33: =IFERROR('11. P&L'!E5/F32,0) -> 6.7847672e+08 | G33: =IFERROR('11. P&L'!F5/G32,0) -> 8.3367216e+08 | H33: Productivité par tête
A34: CA / chantier moyen | B34: FCFA | C34: =IFERROR('11. P&L'!B5/'3. Pipeline & Backlog'!B7,0) -> 1.4198131e+09 | D34: =IFERROR('11. P&L'!C5/'3. Pipeline & Backlog'!C7,0) -> 3.4348292e+09 | E34: =IFERROR('11. P&L'!D5/'3. Pipeline & Backlog'!D7,0) -> 4.0035289e+09 | F34: =IFERROR('11. P&L'!E5/'3. Pipeline & Backlog'!E7,0) -> 4.9278835e+09 | G34: =IFERROR('11. P&L'!F5/'3. Pipeline & Backlog'!F7,0) -> 5.5094856e+09 | H34: Valeur moyenne par chantier

Sheet 14. Scénarios
A1: ANALYSE DE SCÉNARIOS — Sensibilités sur Année 3
A3: Indicateur | B3: Pessimiste | C3: Base (réf Y3) | D3: Optimiste | H3: Commentaire
A4: AJUSTEMENTS PAR SCÉNARIO
A5: Hit-rate AO (impact pipeline) | B5: -0.1 | C5: 0 | D5: 0.07 | H5: Variation pp
A6: Marge brute chantier | B6: -0.03 | C6: 0 | D6: 0.02 | H6: Variation pp
A7: DSO Etat (jours) | B7: 25 | C7: 0 | D7: -15 | H7: Variation jours
A8: Avenants/révision | B8: -0.03 | C8: 0 | D8: 0.03 | H8: Variation pp
A9: Charges fixes (vs base) | B9: 0.15 | C9: 0 | D9: -0.08 | H9: Variation %
A11: RÉSULTATS Y3 PAR SCÉNARIO
A12: Chiffre d'affaires | B12: =C12*0.78 -> 4.9964041e+10 | C12: ='11. P&L'!D5 -> 6.4056463e+10 | D12: =C12*1.15 -> 7.3664932e+10
A13: Marge brute chantier | B13: =B12*(IFERROR('11. P&L'!D12/'11. P&L'!D5,0)-0.03) -> 9.2556027e+09 | C13: ='11. P&L'!D12 -> 1.3787851e+10 | D13: =D12*(IFERROR('11. P&L'!D12/'11. P&L'!D5,0)+0.02) -> 1.7329328e+10
A14: Charges fixes structure | B14: =C14*1.15 -> 4116310000 | C14: =-'11. P&L'!D15 -> 3579400000 | D14: =C14*0.92 -> 3293048000
A15: EBITDA | B15: =B13-B14 -> 5.1392927e+09 | C15: =C13-C14 -> 1.0208451e+10 | D15: =D13-D14 -> 1.403628e+10
A16: Marge EBITDA | B16: =IFERROR(B15/B12,0) -> 0.10285983 | C16: =IFERROR(C15/C12,0) -> 0.15936645 | D16: =IFERROR(D15/D12,0) -> 0.19054222
A17: BFR opérationnel | B17: =C17*1.22 -> 1.8358009e+10 | C17: ='6. BFR & cautions'!D19 -> 1.5047548e+10 | D17: =C17*0.88 -> 1.3241842e+10
A19: SYNTHÈSE & VERDICT
A20: Cash-out additionnel requis vs base | B20: =(C17-B17)+(C15-B15) -> 1.7586979e+09 | C20: 0 | D20: =(C17-D17)+(D15-C15) -> 5.6335341e+09
